{
    "code": "1000",
    "msg": "成功",
    "data": {
        "zhiding": [],
        "list": [
            {
                "id": "16975",
                "title": "5个放松行为其实很损耗气血",
                "titles": [
                    "5个放松行为其实很损耗气血"
                ],
                "hot_icon_type": "3",
                "sort_last": "1",
                "wap_url": "sinaweibo://searchall?q=%235%E4%B8%AA%E6%94%BE%E6%9D%BE%E8%A1%8C%E4%B8%BA%E5%85%B6%E5%AE%9E%E5%BE%88%E6%8D%9F%E8%80%97%E6%B0%94%E8%A1%80%23",
                "sort_now": "1",
                "hot_val": "291886",
                "show_times": "1",
                "hot_icon_url": "",
                "wb_jump_type": 1,
                "start_at": "1732689795",
                "pics": [],
                "title_pic": "",
                "title_type": "0",
                "original_topic_name": "5个放松行为其实很损耗气血",
                "guanggao_at": "0",
                "title_topic_summary": "气血不足的临床表现非常广泛，“气虚”和“血虚”可单独出现，也可合并出现。",
                "create_at": "1732689795",
                "is_hotsearch": "1",
                "icon": "//simg.s.weibo.com/20200928_hot.png",
                "create_dt": "2024-11-27 14:43:15",
                "input_time": "1732689795",
                "is_ad": 0,
                "news_id": "HB-1-qichefe_superpage_hottopic/hottopic-topic_4550016",
                "wburl": "https://s.weibo.com/weibo?q=%235%E4%B8%AA%E6%94%BE%E6%9D%BE%E8%A1%8C%E4%B8%BA%E5%85%B6%E5%AE%9E%E5%BE%88%E6%8D%9F%E8%80%97%E6%B0%94%E8%A1%80%23"
            },
            {
                "id": "16956",
                "title": "长期碎片化睡眠患老年痴呆风险增加",
                "titles": [
                    "长期碎片化睡眠患老年痴呆风险增加"
                ],
                "hot_icon_type": "3",
                "sort_last": "1",
                "wap_url": "sinaweibo://searchall?q=%23%E9%95%BF%E6%9C%9F%E7%A2%8E%E7%89%87%E5%8C%96%E7%9D%A1%E7%9C%A0%E6%82%A3%E8%80%81%E5%B9%B4%E7%97%B4%E5%91%86%E9%A3%8E%E9%99%A9%E5%A2%9E%E5%8A%A0%23",
                "sort_now": "2",
                "hot_val": "154768",
                "show_times": "1",
                "hot_icon_url": "",
                "wb_jump_type": 1,
                "start_at": "1732689480",
                "pics": [],
                "title_pic": "",
                "title_type": "0",
                "original_topic_name": "长期碎片化睡眠患老年痴呆风险增加",
                "guanggao_at": "0",
                "title_topic_summary": "",
                "create_at": "1732689480",
                "is_hotsearch": "-1",
                "icon": "//simg.s.weibo.com/20200928_hot.png",
                "create_dt": "2024-11-27 14:38:00",
                "input_time": "1732689480",
                "is_ad": 0,
                "news_id": "HB-1-qichefe_superpage_hottopic/hottopic-topic_4549517",
                "wburl": "https://s.weibo.com/weibo?q=%23%E9%95%BF%E6%9C%9F%E7%A2%8E%E7%89%87%E5%8C%96%E7%9D%A1%E7%9C%A0%E6%82%A3%E8%80%81%E5%B9%B4%E7%97%B4%E5%91%86%E9%A3%8E%E9%99%A9%E5%A2%9E%E5%8A%A0%23"
            },
            {
                "id": "16919",
                "title": "6个症状说明你的血压可能超标",
                "titles": [
                    "6个症状说明你的血压可能超标"
                ],
                "hot_icon_type": "3",
                "sort_last": "1",
                "wap_url": "sinaweibo://searchall?q=%236%E4%B8%AA%E7%97%87%E7%8A%B6%E8%AF%B4%E6%98%8E%E4%BD%A0%E7%9A%84%E8%A1%80%E5%8E%8B%E5%8F%AF%E8%83%BD%E8%B6%85%E6%A0%87%23",
                "sort_now": "3",
                "hot_val": "139443",
                "show_times": "1",
                "hot_icon_url": "",
                "wb_jump_type": 1,
                "start_at": "1732608877",
                "pics": [],
                "title_pic": "",
                "title_type": "0",
                "original_topic_name": "6个症状说明你的血压可能超标",
                "guanggao_at": "0",
                "title_topic_summary": "世界卫生组织数据显示，我国高血压诊断率为 52%，治疗率为39%，治疗达标率仅为16%。",
                "create_at": "1732608877",
                "is_hotsearch": "-1",
                "icon": "//simg.s.weibo.com/20200928_hot.png",
                "create_dt": "2024-11-26 16:14:37",
                "input_time": "1732608877",
                "is_ad": 0,
                "news_id": "HB-1-qichefe_superpage_hottopic/hottopic-topic_4548103",
                "wburl": "https://s.weibo.com/weibo?q=%236%E4%B8%AA%E7%97%87%E7%8A%B6%E8%AF%B4%E6%98%8E%E4%BD%A0%E7%9A%84%E8%A1%80%E5%8E%8B%E5%8F%AF%E8%83%BD%E8%B6%85%E6%A0%87%23"
            },
            {
                "id": "16918",
                "title": "近八成患者无法管好高血压",
                "titles": [
                    "近八成患者无法管好高血压"
                ],
                "hot_icon_type": "0",
                "sort_last": "1",
                "wap_url": "sinaweibo://searchall?q=%23%E8%BF%91%E5%85%AB%E6%88%90%E6%82%A3%E8%80%85%E6%97%A0%E6%B3%95%E7%AE%A1%E5%A5%BD%E9%AB%98%E8%A1%80%E5%8E%8B%23",
                "sort_now": "4",
                "hot_val": "123728",
                "show_times": "1",
                "hot_icon_url": "",
                "wb_jump_type": 1,
                "start_at": "1732608872",
                "pics": [],
                "title_pic": "",
                "title_type": "0",
                "original_topic_name": "近八成患者无法管好高血压",
                "guanggao_at": "0",
                "title_topic_summary": "世界卫生组织数据显示，我国高血压诊断率为 52%，治疗率为39%，治疗达标率仅为16%。",
                "create_at": "1732608872",
                "is_hotsearch": "-1",
                "icon": "",
                "create_dt": "2024-11-26 16:14:32",
                "input_time": "1732608872",
                "is_ad": 0,
                "news_id": "HB-1-qichefe_superpage_hottopic/hottopic-topic_4548091",
                "wburl": "https://s.weibo.com/weibo?q=%23%E8%BF%91%E5%85%AB%E6%88%90%E6%82%A3%E8%80%85%E6%97%A0%E6%B3%95%E7%AE%A1%E5%A5%BD%E9%AB%98%E8%A1%80%E5%8E%8B%23"
            },
            {
                "id": "16976",
                "title": "同名药药效真的⼀致吗",
                "titles": [
                    "同名药药效真的⼀致吗"
                ],
                "hot_icon_type": "0",
                "sort_last": "0",
                "wap_url": "sinaweibo://searchall?q=%23%E5%90%8C%E5%90%8D%E8%8D%AF%E8%8D%AF%E6%95%88%E7%9C%9F%E7%9A%84%E2%BC%80%E8%87%B4%E5%90%97%23",
                "sort_now": "5",
                "hot_val": "116447",
                "show_times": "1",
                "hot_icon_url": "",
                "wb_jump_type": 1,
                "start_at": "1732689825",
                "pics": [],
                "title_pic": "",
                "title_type": "0",
                "original_topic_name": "同名药药效真的⼀致吗",
                "guanggao_at": "0",
                "title_topic_summary": "近年来市场上同名药大幅增加，同名药存在包装相似，疗效参差、药效不⼀等情况。",
                "create_at": "1732689825",
                "is_hotsearch": "-1",
                "icon": "",
                "create_dt": "2024-11-27 14:43:45",
                "input_time": "1732689825",
                "is_ad": 0,
                "news_id": "HB-1-qichefe_superpage_hottopic/hottopic-topic_4550037",
                "wburl": "https://s.weibo.com/weibo?q=%23%E5%90%8C%E5%90%8D%E8%8D%AF%E8%8D%AF%E6%95%88%E7%9C%9F%E7%9A%84%E2%BC%80%E8%87%B4%E5%90%97%23"
            },
            {
                "id": "16962",
                "title": "预防儿童冬季呼吸道感染的措施",
                "titles": [
                    "预防儿童冬季呼吸道感染的措施"
                ],
                "hot_icon_type": "0",
                "sort_last": "1",
                "wap_url": "sinaweibo://searchall?q=%23%E9%A2%84%E9%98%B2%E5%84%BF%E7%AB%A5%E5%86%AC%E5%AD%A3%E5%91%BC%E5%90%B8%E9%81%93%E6%84%9F%E6%9F%93%E7%9A%84%E6%8E%AA%E6%96%BD%23",
                "sort_now": "6",
                "hot_val": "89454",
                "show_times": "1",
                "hot_icon_url": "",
                "wb_jump_type": 1,
                "start_at": "1732689568",
                "pics": [],
                "title_pic": "",
                "title_type": "0",
                "original_topic_name": "预防儿童冬季呼吸道感染的措施",
                "guanggao_at": "0",
                "title_topic_summary": "儿童冬季易患呼吸道感染。孩子感染后多有发热、咳嗽等症状，儿童为什么相对容易发生呼吸道感染？支原体肺炎、流感、呼吸道合胞病毒感染症状有何不同？如何预防感染？来听听国家儿童医学中心权威专家是如何解答的。",
                "create_at": "1732689568",
                "is_hotsearch": "-1",
                "icon": "",
                "create_dt": "2024-11-27 14:39:28",
                "input_time": "1732689568",
                "is_ad": 0,
                "news_id": "HB-1-qichefe_superpage_hottopic/hottopic-topic_4549700",
                "wburl": "https://s.weibo.com/weibo?q=%23%E9%A2%84%E9%98%B2%E5%84%BF%E7%AB%A5%E5%86%AC%E5%AD%A3%E5%91%BC%E5%90%B8%E9%81%93%E6%84%9F%E6%9F%93%E7%9A%84%E6%8E%AA%E6%96%BD%23"
            },
            {
                "id": "16998",
                "title": "冬天不宜减肥其实是错的",
                "titles": [
                    "冬天不宜减肥其实是错的"
                ],
                "hot_icon_type": "0",
                "sort_last": "1",
                "wap_url": "sinaweibo://searchall?q=%23%E5%86%AC%E5%A4%A9%E4%B8%8D%E5%AE%9C%E5%87%8F%E8%82%A5%E5%85%B6%E5%AE%9E%E6%98%AF%E9%94%99%E7%9A%84%23",
                "sort_now": "7",
                "hot_val": "89058",
                "show_times": "1",
                "hot_icon_url": "",
                "wb_jump_type": 1,
                "start_at": "1732704586",
                "pics": [],
                "title_pic": "",
                "title_type": "0",
                "original_topic_name": "冬天不宜减肥其实是错的",
                "guanggao_at": "0",
                "title_topic_summary": "棕色脂肪是一种能够产生热量并消耗热量的脂肪组织。人体中的棕色脂肪越多，减肥也越容易。好消息是，这种神奇的脂肪会在寒冷环境中，被诱导出来。",
                "create_at": "1732704586",
                "is_hotsearch": "1",
                "icon": "",
                "create_dt": "2024-11-27 18:49:46",
                "input_time": "1732704586",
                "is_ad": 0,
                "news_id": "HB-1-qichefe_superpage_hottopic/hottopic-topic_4551406",
                "wburl": "https://s.weibo.com/weibo?q=%23%E5%86%AC%E5%A4%A9%E4%B8%8D%E5%AE%9C%E5%87%8F%E8%82%A5%E5%85%B6%E5%AE%9E%E6%98%AF%E9%94%99%E7%9A%84%23"
            },
            {
                "id": "16846",
                "title": "尿酸高不痛就没事吗",
                "titles": [
                    "尿酸高不痛就没事吗"
                ],
                "hot_icon_type": "0",
                "sort_last": "1",
                "wap_url": "sinaweibo://searchall?q=%23%E5%B0%BF%E9%85%B8%E9%AB%98%E4%B8%8D%E7%97%9B%E5%B0%B1%E6%B2%A1%E4%BA%8B%E5%90%97%23",
                "sort_now": "8",
                "hot_val": "78853",
                "show_times": "1",
                "hot_icon_url": "",
                "wb_jump_type": 1,
                "start_at": "1732528592",
                "pics": [],
                "title_pic": "",
                "title_type": "0",
                "original_topic_name": "尿酸高不痛就没事吗",
                "guanggao_at": "0",
                "title_topic_summary": "",
                "create_at": "1732528592",
                "is_hotsearch": "-1",
                "icon": "",
                "create_dt": "2024-11-25 17:56:32",
                "input_time": "1732528592",
                "is_ad": 0,
                "news_id": "HB-1-qichefe_superpage_hottopic/hottopic-topic_4545748",
                "wburl": "https://s.weibo.com/weibo?q=%23%E5%B0%BF%E9%85%B8%E9%AB%98%E4%B8%8D%E7%97%9B%E5%B0%B1%E6%B2%A1%E4%BA%8B%E5%90%97%23"
            },
            {
                "id": "16945",
                "title": "骨质疏松症高发人群有哪些",
                "titles": [
                    "骨质疏松症高发人群有哪些"
                ],
                "hot_icon_type": "0",
                "sort_last": "1",
                "wap_url": "sinaweibo://searchall?q=%23%E9%AA%A8%E8%B4%A8%E7%96%8F%E6%9D%BE%E7%97%87%E9%AB%98%E5%8F%91%E4%BA%BA%E7%BE%A4%E6%9C%89%E5%93%AA%E4%BA%9B%23",
                "sort_now": "9",
                "hot_val": "70959",
                "show_times": "1",
                "hot_icon_url": "",
                "wb_jump_type": 1,
                "start_at": "1732689279",
                "pics": [],
                "title_pic": "",
                "title_type": "0",
                "original_topic_name": "骨质疏松症高发人群有哪些",
                "guanggao_at": "0",
                "title_topic_summary": "骨质疏松症不再只是“老年病”，越来越多的年轻人也受到困扰，希望伙伴们引起重视，及早预防远离骨质疏松症。",
                "create_at": "1732689279",
                "is_hotsearch": "1",
                "icon": "",
                "create_dt": "2024-11-27 14:34:39",
                "input_time": "1732689279",
                "is_ad": 0,
                "news_id": "HB-1-qichefe_superpage_hottopic/hottopic-topic_4549182",
                "wburl": "https://s.weibo.com/weibo?q=%23%E9%AA%A8%E8%B4%A8%E7%96%8F%E6%9D%BE%E7%97%87%E9%AB%98%E5%8F%91%E4%BA%BA%E7%BE%A4%E6%9C%89%E5%93%AA%E4%BA%9B%23"
            },
            {
                "id": "17001",
                "title": "冷空气刺激后心衰患者要警惕",
                "titles": [
                    "冷空气刺激后心衰患者要警惕"
                ],
                "hot_icon_type": "0",
                "sort_last": "1",
                "wap_url": "sinaweibo://searchall?q=%23%E5%86%B7%E7%A9%BA%E6%B0%94%E5%88%BA%E6%BF%80%E5%90%8E%E5%BF%83%E8%A1%B0%E6%82%A3%E8%80%85%E8%A6%81%E8%AD%A6%E6%83%95%23",
                "sort_now": "10",
                "hot_val": "62730",
                "show_times": "1",
                "hot_icon_url": "",
                "wb_jump_type": 1,
                "start_at": "1732704664",
                "pics": [],
                "title_pic": "",
                "title_type": "0",
                "original_topic_name": "冷空气刺激后心衰患者要警惕",
                "guanggao_at": "0",
                "title_topic_summary": "寒潮来袭，气温骤降。医生介绍，每到冬季，心梗患者都会明显增加，因为寒冷空气会让血管痉挛，血液黏稠度增加，也会导致血压不稳定。",
                "create_at": "1732704664",
                "is_hotsearch": "-1",
                "icon": "",
                "create_dt": "2024-11-27 18:51:04",
                "input_time": "1732704664",
                "is_ad": 0,
                "news_id": "HB-1-qichefe_superpage_hottopic/hottopic-topic_4551607",
                "wburl": "https://s.weibo.com/weibo?q=%23%E5%86%B7%E7%A9%BA%E6%B0%94%E5%88%BA%E6%BF%80%E5%90%8E%E5%BF%83%E8%A1%B0%E6%82%A3%E8%80%85%E8%A6%81%E8%AD%A6%E6%83%95%23"
            },
            {
                "id": "16905",
                "title": "3个御寒误区可能影响健康",
                "titles": [
                    "3个御寒误区可能影响健康"
                ],
                "hot_icon_type": "0",
                "sort_last": "1",
                "wap_url": "sinaweibo://searchall?q=%233%E4%B8%AA%E5%BE%A1%E5%AF%92%E8%AF%AF%E5%8C%BA%E5%8F%AF%E8%83%BD%E5%BD%B1%E5%93%8D%E5%81%A5%E5%BA%B7%23",
                "sort_now": "11",
                "hot_val": "59433",
                "show_times": "1",
                "hot_icon_url": "",
                "wb_jump_type": 1,
                "start_at": "1732608697",
                "pics": [],
                "title_pic": "",
                "title_type": "0",
                "original_topic_name": "3个御寒误区可能影响健康",
                "guanggao_at": "0",
                "title_topic_summary": "",
                "create_at": "1732608697",
                "is_hotsearch": "-1",
                "icon": "",
                "create_dt": "2024-11-26 16:11:37",
                "input_time": "1732608697",
                "is_ad": 0,
                "news_id": "HB-1-qichefe_superpage_hottopic/hottopic-topic_4547686",
                "wburl": "https://s.weibo.com/weibo?q=%233%E4%B8%AA%E5%BE%A1%E5%AF%92%E8%AF%AF%E5%8C%BA%E5%8F%AF%E8%83%BD%E5%BD%B1%E5%93%8D%E5%81%A5%E5%BA%B7%23"
            },
            {
                "id": "16831",
                "title": "医生科普主动脉夹层有多凶险",
                "titles": [
                    "医生科普主动脉夹层有多凶险"
                ],
                "hot_icon_type": "0",
                "sort_last": "1",
                "wap_url": "sinaweibo://searchall?q=%23%E5%8C%BB%E7%94%9F%E7%A7%91%E6%99%AE%E4%B8%BB%E5%8A%A8%E8%84%89%E5%A4%B9%E5%B1%82%E6%9C%89%E5%A4%9A%E5%87%B6%E9%99%A9%23",
                "sort_now": "12",
                "hot_val": "53716",
                "show_times": "1",
                "hot_icon_url": "",
                "wb_jump_type": 1,
                "start_at": "1732528002",
                "pics": [],
                "title_pic": "",
                "title_type": "0",
                "original_topic_name": "医生科普主动脉夹层有多凶险",
                "guanggao_at": "0",
                "title_topic_summary": "西安交大一附院医生向记者介绍，主动脉夹层外膜一旦破裂， 一两分钟血液流完，基本就没有抢救的机会了。冬季是“主动脉夹层”高发时段，如果出现了剧烈的胸背痛，建议尽快到医院检查，排除风险。",
                "create_at": "1732528002",
                "is_hotsearch": "-1",
                "icon": "",
                "create_dt": "2024-11-25 17:46:42",
                "input_time": "1732528002",
                "is_ad": 0,
                "news_id": "HB-1-qichefe_superpage_hottopic/hottopic-topic_4544841",
                "wburl": "https://s.weibo.com/weibo?q=%23%E5%8C%BB%E7%94%9F%E7%A7%91%E6%99%AE%E4%B8%BB%E5%8A%A8%E8%84%89%E5%A4%B9%E5%B1%82%E6%9C%89%E5%A4%9A%E5%87%B6%E9%99%A9%23"
            },
            {
                "id": "16920",
                "title": "入冬了如何管理高血压",
                "titles": [
                    "入冬了如何管理高血压"
                ],
                "hot_icon_type": "0",
                "sort_last": "1",
                "wap_url": "sinaweibo://searchall?q=%E5%85%A5%E5%86%AC%E4%BA%86%E5%A6%82%E4%BD%95%E7%AE%A1%E7%90%86%E9%AB%98%E8%A1%80%E5%8E%8B",
                "sort_now": "13",
                "hot_val": "50114",
                "show_times": "1",
                "hot_icon_url": "",
                "wb_jump_type": 2,
                "start_at": "1732608880",
                "pics": [],
                "title_pic": "",
                "title_type": "0",
                "original_topic_name": "入冬了如何管理高血压",
                "guanggao_at": "0",
                "title_topic_summary": "入冬如何管理高血压？！",
                "create_at": "1732608880",
                "is_hotsearch": "-1",
                "icon": "",
                "create_dt": "2024-11-26 16:14:40",
                "input_time": "1732608880",
                "is_ad": 0,
                "news_id": "HB-1-qichefe_superpage_hottopic/hottopic-topic_4548124",
                "wburl": "https://s.weibo.com/weibo?q=%E5%85%A5%E5%86%AC%E4%BA%86%E5%A6%82%E4%BD%95%E7%AE%A1%E7%90%86%E9%AB%98%E8%A1%80%E5%8E%8B"
            },
            {
                "id": "16845",
                "title": "更适合大学生的减肥动作",
                "titles": [
                    "更适合大学生的减肥动作"
                ],
                "hot_icon_type": "0",
                "sort_last": "1",
                "wap_url": "sinaweibo://searchall?q=%23%E6%9B%B4%E9%80%82%E5%90%88%E5%A4%A7%E5%AD%A6%E7%94%9F%E7%9A%84%E5%87%8F%E8%82%A5%E5%8A%A8%E4%BD%9C%23",
                "sort_now": "14",
                "hot_val": "49532",
                "show_times": "1",
                "hot_icon_url": "",
                "wb_jump_type": 1,
                "start_at": "1732528560",
                "pics": [],
                "title_pic": "",
                "title_type": "0",
                "original_topic_name": "更适合大学生的减肥动作",
                "guanggao_at": "0",
                "title_topic_summary": "",
                "create_at": "1732528560",
                "is_hotsearch": "-1",
                "icon": "",
                "create_dt": "2024-11-25 17:56:00",
                "input_time": "1732528560",
                "is_ad": 0,
                "news_id": "HB-1-qichefe_superpage_hottopic/hottopic-topic_4545661",
                "wburl": "https://s.weibo.com/weibo?q=%23%E6%9B%B4%E9%80%82%E5%90%88%E5%A4%A7%E5%AD%A6%E7%94%9F%E7%9A%84%E5%87%8F%E8%82%A5%E5%8A%A8%E4%BD%9C%23"
            },
            {
                "id": "16999",
                "title": "体质差医生建议吃干红枣",
                "titles": [
                    "体质差医生建议吃干红枣"
                ],
                "hot_icon_type": "0",
                "sort_last": "1",
                "wap_url": "sinaweibo://searchall?q=%23%E4%BD%93%E8%B4%A8%E5%B7%AE%E5%8C%BB%E7%94%9F%E5%BB%BA%E8%AE%AE%E5%90%83%E5%B9%B2%E7%BA%A2%E6%9E%A3%23",
                "sort_now": "15",
                "hot_val": "47583",
                "show_times": "1",
                "hot_icon_url": "",
                "wb_jump_type": 1,
                "start_at": "1732704644",
                "pics": [],
                "title_pic": "",
                "title_type": "0",
                "original_topic_name": "体质差医生建议吃干红枣",
                "guanggao_at": "0",
                "title_topic_summary": "胃寒，免疫功能低下，没精神，体质差爱生病？老中医建议吃枣缓解：每天吃3-5颗，一定要是干的红枣，煮水或者煮粥效果更好，可以补血健脾。快收藏用起来吧！",
                "create_at": "1732704644",
                "is_hotsearch": "-1",
                "icon": "",
                "create_dt": "2024-11-27 18:50:44",
                "input_time": "1732704644",
                "is_ad": 0,
                "news_id": "HB-1-qichefe_superpage_hottopic/hottopic-topic_4551586",
                "wburl": "https://s.weibo.com/weibo?q=%23%E4%BD%93%E8%B4%A8%E5%B7%AE%E5%8C%BB%E7%94%9F%E5%BB%BA%E8%AE%AE%E5%90%83%E5%B9%B2%E7%BA%A2%E6%9E%A3%23"
            },
            {
                "id": "16894",
                "title": "盲目服用中药易致药物性肝损伤",
                "titles": [
                    "盲目服用中药易致药物性肝损伤"
                ],
                "hot_icon_type": "0",
                "sort_last": "-1",
                "wap_url": "sinaweibo://searchall?q=%23%E7%9B%B2%E7%9B%AE%E6%9C%8D%E7%94%A8%E4%B8%AD%E8%8D%AF%E6%98%93%E8%87%B4%E8%8D%AF%E7%89%A9%E6%80%A7%E8%82%9D%E6%8D%9F%E4%BC%A4%23",
                "sort_now": "16",
                "hot_val": "43648",
                "show_times": "1",
                "hot_icon_url": "",
                "wb_jump_type": 1,
                "start_at": "1732608606",
                "pics": [],
                "title_pic": "",
                "title_type": "0",
                "original_topic_name": "盲目服用中药易致药物性肝损伤",
                "guanggao_at": "0",
                "title_topic_summary": "服用任何药物都应遵医嘱，即使是医生所开方，长期服用也需密切复查肝功能！",
                "create_at": "1732608606",
                "is_hotsearch": "-1",
                "icon": "",
                "create_dt": "2024-11-26 16:10:06",
                "input_time": "1732608606",
                "is_ad": 0,
                "news_id": "HB-1-qichefe_superpage_hottopic/hottopic-topic_4547411",
                "wburl": "https://s.weibo.com/weibo?q=%23%E7%9B%B2%E7%9B%AE%E6%9C%8D%E7%94%A8%E4%B8%AD%E8%8D%AF%E6%98%93%E8%87%B4%E8%8D%AF%E7%89%A9%E6%80%A7%E8%82%9D%E6%8D%9F%E4%BC%A4%23"
            },
            {
                "id": "16988",
                "title": "这3种药片不要随意掰开吃",
                "titles": [
                    "这3种药片不要随意掰开吃"
                ],
                "hot_icon_type": "0",
                "sort_last": "-1",
                "wap_url": "sinaweibo://searchall?q=%E8%BF%993%E7%A7%8D%E8%8D%AF%E7%89%87%E4%B8%8D%E8%A6%81%E9%9A%8F%E6%84%8F%E6%8E%B0%E5%BC%80%E5%90%83",
                "sort_now": "17",
                "hot_val": "36379",
                "show_times": "1",
                "hot_icon_url": "",
                "wb_jump_type": 2,
                "start_at": "1732690062",
                "pics": [],
                "title_pic": "",
                "title_type": "0",
                "original_topic_name": "这3种药片不要随意掰开吃",
                "guanggao_at": "0",
                "title_topic_summary": "",
                "create_at": "1732690062",
                "is_hotsearch": "-1",
                "icon": "",
                "create_dt": "2024-11-27 14:47:42",
                "input_time": "1732690062",
                "is_ad": 0,
                "news_id": "HB-1-qichefe_superpage_hottopic/hottopic-topic_4550811",
                "wburl": "https://s.weibo.com/weibo?q=%E8%BF%993%E7%A7%8D%E8%8D%AF%E7%89%87%E4%B8%8D%E8%A6%81%E9%9A%8F%E6%84%8F%E6%8E%B0%E5%BC%80%E5%90%83"
            },
            {
                "id": "16838",
                "title": "代糖不能帮助减肥",
                "titles": [
                    "代糖不能帮助减肥"
                ],
                "hot_icon_type": "0",
                "sort_last": "1",
                "wap_url": "sinaweibo://searchall?q=%E4%BB%A3%E7%B3%96%E4%B8%8D%E8%83%BD%E5%B8%AE%E5%8A%A9%E5%87%8F%E8%82%A5",
                "sort_now": "18",
                "hot_val": "35656",
                "show_times": "1",
                "hot_icon_url": "",
                "wb_jump_type": 2,
                "start_at": "1732528363",
                "pics": [],
                "title_pic": "",
                "title_type": "0",
                "original_topic_name": "代糖不能帮助减肥",
                "guanggao_at": "0",
                "title_topic_summary": "",
                "create_at": "1732528363",
                "is_hotsearch": "-1",
                "icon": "",
                "create_dt": "2024-11-25 17:52:43",
                "input_time": "1732528363",
                "is_ad": 0,
                "news_id": "HB-1-qichefe_superpage_hottopic/hottopic-topic_4545263",
                "wburl": "https://s.weibo.com/weibo?q=%E4%BB%A3%E7%B3%96%E4%B8%8D%E8%83%BD%E5%B8%AE%E5%8A%A9%E5%87%8F%E8%82%A5"
            },
            {
                "id": "16964",
                "title": "降温后要尤其当心心脑血管病",
                "titles": [
                    "降温后要尤其当心心脑血管病"
                ],
                "hot_icon_type": "0",
                "sort_last": "1",
                "wap_url": "sinaweibo://searchall?q=%23%E9%99%8D%E6%B8%A9%E5%90%8E%E8%A6%81%E5%B0%A4%E5%85%B6%E5%BD%93%E5%BF%83%E5%BF%83%E8%84%91%E8%A1%80%E7%AE%A1%E7%97%85%23",
                "sort_now": "19",
                "hot_val": "34448",
                "show_times": "1",
                "hot_icon_url": "",
                "wb_jump_type": 1,
                "start_at": "1732689597",
                "pics": [],
                "title_pic": "",
                "title_type": "0",
                "original_topic_name": "降温后要尤其当心心脑血管病",
                "guanggao_at": "0",
                "title_topic_summary": "",
                "create_at": "1732689597",
                "is_hotsearch": "-1",
                "icon": "",
                "create_dt": "2024-11-27 14:39:57",
                "input_time": "1732689597",
                "is_ad": 0,
                "news_id": "HB-1-qichefe_superpage_hottopic/hottopic-topic_4549738",
                "wburl": "https://s.weibo.com/weibo?q=%23%E9%99%8D%E6%B8%A9%E5%90%8E%E8%A6%81%E5%B0%A4%E5%85%B6%E5%BD%93%E5%BF%83%E5%BF%83%E8%84%91%E8%A1%80%E7%AE%A1%E7%97%85%23"
            },
            {
                "id": "16862",
                "title": "中医推荐真正的暖身妙招",
                "titles": [
                    "中医推荐真正的暖身妙招"
                ],
                "hot_icon_type": "0",
                "sort_last": "1",
                "wap_url": "sinaweibo://searchall?q=%E4%B8%AD%E5%8C%BB%E6%8E%A8%E8%8D%90%E7%9C%9F%E6%AD%A3%E7%9A%84%E6%9A%96%E8%BA%AB%E5%A6%99%E6%8B%9B",
                "sort_now": "20",
                "hot_val": "32880",
                "show_times": "1",
                "hot_icon_url": "",
                "wb_jump_type": 2,
                "start_at": "1732587212",
                "pics": [],
                "title_pic": "",
                "title_type": "0",
                "original_topic_name": "中医推荐真正的暖身妙招",
                "guanggao_at": "0",
                "title_topic_summary": "",
                "create_at": "1732587212",
                "is_hotsearch": "-1",
                "icon": "",
                "create_dt": "2024-11-26 10:13:32",
                "input_time": "1732587212",
                "is_ad": 0,
                "news_id": "HB-1-qichefe_superpage_hottopic/hottopic-topic_4546583",
                "wburl": "https://s.weibo.com/weibo?q=%E4%B8%AD%E5%8C%BB%E6%8E%A8%E8%8D%90%E7%9C%9F%E6%AD%A3%E7%9A%84%E6%9A%96%E8%BA%AB%E5%A6%99%E6%8B%9B"
            },
            {
                "id": "16957",
                "title": "天气骤冷易诱发心脑血管疾病",
                "titles": [
                    "天气骤冷易诱发心脑血管疾病"
                ],
                "hot_icon_type": "0",
                "sort_last": "1",
                "wap_url": "sinaweibo://searchall?q=%23%E5%A4%A9%E6%B0%94%E9%AA%A4%E5%86%B7%E6%98%93%E8%AF%B1%E5%8F%91%E5%BF%83%E8%84%91%E8%A1%80%E7%AE%A1%E7%96%BE%E7%97%85%23",
                "sort_now": "21",
                "hot_val": "32301",
                "show_times": "1",
                "hot_icon_url": "",
                "wb_jump_type": 1,
                "start_at": "1732689485",
                "pics": [],
                "title_pic": "",
                "title_type": "0",
                "original_topic_name": "天气骤冷易诱发心脑血管疾病",
                "guanggao_at": "0",
                "title_topic_summary": "近期我国大部分地区降温明显，降温后室内外温差加大，天气骤冷易诱发心脑血管疾病。寒冷的空气会让血管痉挛，血液黏稠度增加，也会导致血压的不稳定，这些都会造成血管内斑块破裂和血栓形成，进而引发心梗。",
                "create_at": "1732689485",
                "is_hotsearch": "-1",
                "icon": "",
                "create_dt": "2024-11-27 14:38:05",
                "input_time": "1732689485",
                "is_ad": 0,
                "news_id": "HB-1-qichefe_superpage_hottopic/hottopic-topic_4549528",
                "wburl": "https://s.weibo.com/weibo?q=%23%E5%A4%A9%E6%B0%94%E9%AA%A4%E5%86%B7%E6%98%93%E8%AF%B1%E5%8F%91%E5%BF%83%E8%84%91%E8%A1%80%E7%AE%A1%E7%96%BE%E7%97%85%23"
            },
            {
                "id": "16965",
                "title": "这类人午睡超过30分钟增加脑梗风险",
                "titles": [
                    "这类人午睡超过30分钟增加脑梗风险"
                ],
                "hot_icon_type": "0",
                "sort_last": "0",
                "wap_url": "sinaweibo://searchall?q=%23%E8%BF%99%E7%B1%BB%E4%BA%BA%E5%8D%88%E7%9D%A1%E8%B6%85%E8%BF%8730%E5%88%86%E9%92%9F%E5%A2%9E%E5%8A%A0%E8%84%91%E6%A2%97%E9%A3%8E%E9%99%A9%23",
                "sort_now": "22",
                "hot_val": "31268",
                "show_times": "1",
                "hot_icon_url": "",
                "wb_jump_type": 1,
                "start_at": "1732689619",
                "pics": [],
                "title_pic": "",
                "title_type": "0",
                "original_topic_name": "这类人午睡超过30分钟增加脑梗风险",
                "guanggao_at": "0",
                "title_topic_summary": "午睡一小觉，精神一整天。但有些特殊人群午睡，或者睡得过久，反而会增加健康风险。",
                "create_at": "1732689619",
                "is_hotsearch": "-1",
                "icon": "",
                "create_dt": "2024-11-27 14:40:19",
                "input_time": "1732689619",
                "is_ad": 0,
                "news_id": "HB-1-qichefe_superpage_hottopic/hottopic-topic_4549757",
                "wburl": "https://s.weibo.com/weibo?q=%23%E8%BF%99%E7%B1%BB%E4%BA%BA%E5%8D%88%E7%9D%A1%E8%B6%85%E8%BF%8730%E5%88%86%E9%92%9F%E5%A2%9E%E5%8A%A0%E8%84%91%E6%A2%97%E9%A3%8E%E9%99%A9%23"
            },
            {
                "id": "16804",
                "title": "太烫的食物会增加食管癌发生风险",
                "titles": [
                    "太烫的食物会增加食管癌发生风险"
                ],
                "hot_icon_type": "0",
                "sort_last": "-1",
                "wap_url": "sinaweibo://searchall?q=%23%E5%A4%AA%E7%83%AB%E7%9A%84%E9%A3%9F%E7%89%A9%E4%BC%9A%E5%A2%9E%E5%8A%A0%E9%A3%9F%E7%AE%A1%E7%99%8C%E5%8F%91%E7%94%9F%E9%A3%8E%E9%99%A9%23",
                "sort_now": "23",
                "hot_val": "30819",
                "show_times": "1",
                "hot_icon_url": "",
                "wb_jump_type": 1,
                "start_at": "1732501304",
                "pics": [],
                "title_pic": "",
                "title_type": "0",
                "original_topic_name": "太烫的食物会增加食管癌发生风险",
                "guanggao_at": "0",
                "title_topic_summary": "天冷了，大家更想吃口热乎的，热汤、热饭、刚出锅的热饺子……专家表示，太烫的食物会增加食管癌发生风险。",
                "create_at": "1732501304",
                "is_hotsearch": "-1",
                "icon": "",
                "create_dt": "2024-11-25 10:21:44",
                "input_time": "1732501304",
                "is_ad": 0,
                "news_id": "HB-1-qichefe_superpage_hottopic/hottopic-topic_4542977",
                "wburl": "https://s.weibo.com/weibo?q=%23%E5%A4%AA%E7%83%AB%E7%9A%84%E9%A3%9F%E7%89%A9%E4%BC%9A%E5%A2%9E%E5%8A%A0%E9%A3%9F%E7%AE%A1%E7%99%8C%E5%8F%91%E7%94%9F%E9%A3%8E%E9%99%A9%23"
            },
            {
                "id": "16850",
                "title": "哪些肺癌患者适合靶向治疗",
                "titles": [
                    "哪些肺癌患者适合靶向治疗"
                ],
                "hot_icon_type": "0",
                "sort_last": "-1",
                "wap_url": "sinaweibo://searchall?q=%23%E5%93%AA%E4%BA%9B%E8%82%BA%E7%99%8C%E6%82%A3%E8%80%85%E9%80%82%E5%90%88%E9%9D%B6%E5%90%91%E6%B2%BB%E7%96%97%23",
                "sort_now": "24",
                "hot_val": "30757",
                "show_times": "1",
                "hot_icon_url": "",
                "wb_jump_type": 1,
                "start_at": "1732530114",
                "pics": [],
                "title_pic": "",
                "title_type": "0",
                "original_topic_name": "哪些肺癌患者适合靶向治疗",
                "guanggao_at": "0",
                "title_topic_summary": "",
                "create_at": "1732530114",
                "is_hotsearch": "-1",
                "icon": "",
                "create_dt": "2024-11-25 18:21:54",
                "input_time": "1732530114",
                "is_ad": 0,
                "news_id": "HB-1-qichefe_superpage_hottopic/hottopic-topic_4546088",
                "wburl": "https://s.weibo.com/weibo?q=%23%E5%93%AA%E4%BA%9B%E8%82%BA%E7%99%8C%E6%82%A3%E8%80%85%E9%80%82%E5%90%88%E9%9D%B6%E5%90%91%E6%B2%BB%E7%96%97%23"
            },
            {
                "id": "16958",
                "title": "这三类人群要警惕气温骤降",
                "titles": [
                    "这三类人群要警惕气温骤降"
                ],
                "hot_icon_type": "0",
                "sort_last": "1",
                "wap_url": "sinaweibo://searchall?q=%23%E8%BF%99%E4%B8%89%E7%B1%BB%E4%BA%BA%E7%BE%A4%E8%A6%81%E8%AD%A6%E6%83%95%E6%B0%94%E6%B8%A9%E9%AA%A4%E9%99%8D%23",
                "sort_now": "25",
                "hot_val": "30171",
                "show_times": "1",
                "hot_icon_url": "",
                "wb_jump_type": 1,
                "start_at": "1732689488",
                "pics": [],
                "title_pic": "",
                "title_type": "0",
                "original_topic_name": "这三类人群要警惕气温骤降",
                "guanggao_at": "0",
                "title_topic_summary": "近期我国大部分地区降温明显，降温后室内外温差加大，天气骤冷易诱发心脑血管疾病。寒冷的空气会让血管痉挛，血液黏稠度增加，也会导致血压的不稳定，这些都会造成血管内斑块破裂和血栓形成，进而引发心梗。",
                "create_at": "1732689488",
                "is_hotsearch": "-1",
                "icon": "",
                "create_dt": "2024-11-27 14:38:08",
                "input_time": "1732689488",
                "is_ad": 0,
                "news_id": "HB-1-qichefe_superpage_hottopic/hottopic-topic_4549529",
                "wburl": "https://s.weibo.com/weibo?q=%23%E8%BF%99%E4%B8%89%E7%B1%BB%E4%BA%BA%E7%BE%A4%E8%A6%81%E8%AD%A6%E6%83%95%E6%B0%94%E6%B8%A9%E9%AA%A4%E9%99%8D%23"
            },
            {
                "id": "16888",
                "title": "爱抠鼻子的人危险了",
                "titles": [
                    "爱抠鼻子的人危险了"
                ],
                "hot_icon_type": "0",
                "sort_last": "1",
                "wap_url": "sinaweibo://searchall?q=%23%E7%88%B1%E6%8A%A0%E9%BC%BB%E5%AD%90%E7%9A%84%E4%BA%BA%E5%8D%B1%E9%99%A9%E4%BA%86%23",
                "sort_now": "26",
                "hot_val": "29536",
                "show_times": "1",
                "hot_icon_url": "",
                "wb_jump_type": 1,
                "start_at": "1732608501",
                "pics": [],
                "title_pic": "",
                "title_type": "0",
                "original_topic_name": "爱抠鼻子的人危险了",
                "guanggao_at": "0",
                "title_topic_summary": "",
                "create_at": "1732608501",
                "is_hotsearch": "-1",
                "icon": "",
                "create_dt": "2024-11-26 16:08:21",
                "input_time": "1732608501",
                "is_ad": 0,
                "news_id": "HB-1-qichefe_superpage_hottopic/hottopic-topic_4547203",
                "wburl": "https://s.weibo.com/weibo?q=%23%E7%88%B1%E6%8A%A0%E9%BC%BB%E5%AD%90%E7%9A%84%E4%BA%BA%E5%8D%B1%E9%99%A9%E4%BA%86%23"
            },
            {
                "id": "16889",
                "title": "为什么很多人无法停止抠鼻子",
                "titles": [
                    "为什么很多人无法停止抠鼻子"
                ],
                "hot_icon_type": "0",
                "sort_last": "1",
                "wap_url": "sinaweibo://searchall?q=%23%E4%B8%BA%E4%BB%80%E4%B9%88%E5%BE%88%E5%A4%9A%E4%BA%BA%E6%97%A0%E6%B3%95%E5%81%9C%E6%AD%A2%E6%8A%A0%E9%BC%BB%E5%AD%90%23",
                "sort_now": "27",
                "hot_val": "29536",
                "show_times": "1",
                "hot_icon_url": "",
                "wb_jump_type": 1,
                "start_at": "1732608508",
                "pics": [],
                "title_pic": "",
                "title_type": "0",
                "original_topic_name": "为什么很多人无法停止抠鼻子",
                "guanggao_at": "0",
                "title_topic_summary": "",
                "create_at": "1732608508",
                "is_hotsearch": "-1",
                "icon": "",
                "create_dt": "2024-11-26 16:08:28",
                "input_time": "1732608508",
                "is_ad": 0,
                "news_id": "HB-1-qichefe_superpage_hottopic/hottopic-topic_4547204",
                "wburl": "https://s.weibo.com/weibo?q=%23%E4%B8%BA%E4%BB%80%E4%B9%88%E5%BE%88%E5%A4%9A%E4%BA%BA%E6%97%A0%E6%B3%95%E5%81%9C%E6%AD%A2%E6%8A%A0%E9%BC%BB%E5%AD%90%23"
            },
            {
                "id": "16833",
                "title": "冬天皮肤干燥的原因是什么",
                "titles": [
                    "冬天皮肤干燥的原因是什么"
                ],
                "hot_icon_type": "0",
                "sort_last": "-1",
                "wap_url": "sinaweibo://searchall?q=%E5%86%AC%E5%A4%A9%E7%9A%AE%E8%82%A4%E5%B9%B2%E7%87%A5%E7%9A%84%E5%8E%9F%E5%9B%A0%E6%98%AF%E4%BB%80%E4%B9%88",
                "sort_now": "28",
                "hot_val": "28744",
                "show_times": "1",
                "hot_icon_url": "",
                "wb_jump_type": 2,
                "start_at": "1732528232",
                "pics": [],
                "title_pic": "",
                "title_type": "0",
                "original_topic_name": "冬天皮肤干燥的原因是什么",
                "guanggao_at": "0",
                "title_topic_summary": "",
                "create_at": "1732528232",
                "is_hotsearch": "-1",
                "icon": "",
                "create_dt": "2024-11-25 17:50:32",
                "input_time": "1732528232",
                "is_ad": 0,
                "news_id": "HB-1-qichefe_superpage_hottopic/hottopic-topic_4545070",
                "wburl": "https://s.weibo.com/weibo?q=%E5%86%AC%E5%A4%A9%E7%9A%AE%E8%82%A4%E5%B9%B2%E7%87%A5%E7%9A%84%E5%8E%9F%E5%9B%A0%E6%98%AF%E4%BB%80%E4%B9%88"
            },
            {
                "id": "16980",
                "title": "同名药药效真的一致吗",
                "titles": [
                    "同名药药效真的一致吗"
                ],
                "hot_icon_type": "0",
                "sort_last": "-1",
                "wap_url": "sinaweibo://searchall?q=%E5%90%8C%E5%90%8D%E8%8D%AF%E8%8D%AF%E6%95%88%E7%9C%9F%E7%9A%84%E4%B8%80%E8%87%B4%E5%90%97",
                "sort_now": "29",
                "hot_val": "28474",
                "show_times": "1",
                "hot_icon_url": "",
                "wb_jump_type": 2,
                "start_at": "1732689932",
                "pics": [],
                "title_pic": "",
                "title_type": "0",
                "original_topic_name": "同名药药效真的一致吗",
                "guanggao_at": "0",
                "title_topic_summary": "",
                "create_at": "1732689932",
                "is_hotsearch": "-1",
                "icon": "",
                "create_dt": "2024-11-27 14:45:32",
                "input_time": "1732689932",
                "is_ad": 0,
                "news_id": "HB-1-qichefe_superpage_hottopic/hottopic-topic_4550400",
                "wburl": "https://s.weibo.com/weibo?q=%E5%90%8C%E5%90%8D%E8%8D%AF%E8%8D%AF%E6%95%88%E7%9C%9F%E7%9A%84%E4%B8%80%E8%87%B4%E5%90%97"
            },
            {
                "id": "16869",
                "title": "大部分人右侧胳膊血压偏高",
                "titles": [
                    "大部分人右侧胳膊血压偏高"
                ],
                "hot_icon_type": "0",
                "sort_last": "1",
                "wap_url": "sinaweibo://searchall?q=%23%E5%A4%A7%E9%83%A8%E5%88%86%E4%BA%BA%E5%8F%B3%E4%BE%A7%E8%83%B3%E8%86%8A%E8%A1%80%E5%8E%8B%E5%81%8F%E9%AB%98%23",
                "sort_now": "30",
                "hot_val": "28447",
                "show_times": "1",
                "hot_icon_url": "",
                "wb_jump_type": 1,
                "start_at": "1732587321",
                "pics": [],
                "title_pic": "",
                "title_type": "0",
                "original_topic_name": "大部分人右侧胳膊血压偏高",
                "guanggao_at": "0",
                "title_topic_summary": "",
                "create_at": "1732587321",
                "is_hotsearch": "-1",
                "icon": "",
                "create_dt": "2024-11-26 10:15:21",
                "input_time": "1732587321",
                "is_ad": 0,
                "news_id": "HB-1-qichefe_superpage_hottopic/hottopic-topic_4546829",
                "wburl": "https://s.weibo.com/weibo?q=%23%E5%A4%A7%E9%83%A8%E5%88%86%E4%BA%BA%E5%8F%B3%E4%BE%A7%E8%83%B3%E8%86%8A%E8%A1%80%E5%8E%8B%E5%81%8F%E9%AB%98%23"
            },
            {
                "id": "16875",
                "title": "医生眼中皮肤就是情绪的镜子",
                "titles": [
                    "医生眼中皮肤就是情绪的镜子"
                ],
                "hot_icon_type": "0",
                "sort_last": "1",
                "wap_url": "sinaweibo://searchall?q=%23%E5%8C%BB%E7%94%9F%E7%9C%BC%E4%B8%AD%E7%9A%AE%E8%82%A4%E5%B0%B1%E6%98%AF%E6%83%85%E7%BB%AA%E7%9A%84%E9%95%9C%E5%AD%90%23",
                "sort_now": "31",
                "hot_val": "27395",
                "show_times": "1",
                "hot_icon_url": "",
                "wb_jump_type": 1,
                "start_at": "1732587356",
                "pics": [],
                "title_pic": "",
                "title_type": "0",
                "original_topic_name": "医生眼中皮肤就是情绪的镜子",
                "guanggao_at": "0",
                "title_topic_summary": "德国天露芬，专研精华油护肤，畅销德国40年，致力于探索有机成分和科学配方，持久有效改善干皮问题，唤醒肌肤自愈力，皮肤干就用天露芬。",
                "create_at": "1732587356",
                "is_hotsearch": "1",
                "icon": "",
                "create_dt": "2024-11-26 10:15:56",
                "input_time": "1732587356",
                "is_ad": 0,
                "news_id": "HB-1-qichefe_superpage_hottopic/hottopic-topic_4546866",
                "wburl": "https://s.weibo.com/weibo?q=%23%E5%8C%BB%E7%94%9F%E7%9C%BC%E4%B8%AD%E7%9A%AE%E8%82%A4%E5%B0%B1%E6%98%AF%E6%83%85%E7%BB%AA%E7%9A%84%E9%95%9C%E5%AD%90%23"
            },
            {
                "id": "16870",
                "title": "测血压左右胳膊不一样以哪个为准",
                "titles": [
                    "测血压左右胳膊不一样以哪个为准"
                ],
                "hot_icon_type": "0",
                "sort_last": "1",
                "wap_url": "sinaweibo://searchall?q=%23%E6%B5%8B%E8%A1%80%E5%8E%8B%E5%B7%A6%E5%8F%B3%E8%83%B3%E8%86%8A%E4%B8%8D%E4%B8%80%E6%A0%B7%E4%BB%A5%E5%93%AA%E4%B8%AA%E4%B8%BA%E5%87%86%23",
                "sort_now": "32",
                "hot_val": "27380",
                "show_times": "1",
                "hot_icon_url": "",
                "wb_jump_type": 1,
                "start_at": "1732587324",
                "pics": [],
                "title_pic": "",
                "title_type": "0",
                "original_topic_name": "测血压左右胳膊不一样以哪个为准",
                "guanggao_at": "0",
                "title_topic_summary": "",
                "create_at": "1732587324",
                "is_hotsearch": "-1",
                "icon": "",
                "create_dt": "2024-11-26 10:15:24",
                "input_time": "1732587324",
                "is_ad": 0,
                "news_id": "HB-1-qichefe_superpage_hottopic/hottopic-topic_4546830",
                "wburl": "https://s.weibo.com/weibo?q=%23%E6%B5%8B%E8%A1%80%E5%8E%8B%E5%B7%A6%E5%8F%B3%E8%83%B3%E8%86%8A%E4%B8%8D%E4%B8%80%E6%A0%B7%E4%BB%A5%E5%93%AA%E4%B8%AA%E4%B8%BA%E5%87%86%23"
            },
            {
                "id": "16946",
                "title": "这类头痛千万别大意",
                "titles": [
                    "这类头痛千万别大意"
                ],
                "hot_icon_type": "0",
                "sort_last": "-1",
                "wap_url": "sinaweibo://searchall?q=%23%E8%BF%99%E7%B1%BB%E5%A4%B4%E7%97%9B%E5%8D%83%E4%B8%87%E5%88%AB%E5%A4%A7%E6%84%8F%23",
                "sort_now": "33",
                "hot_val": "27251",
                "show_times": "1",
                "hot_icon_url": "",
                "wb_jump_type": 1,
                "start_at": "1732689308",
                "pics": [],
                "title_pic": "",
                "title_type": "0",
                "original_topic_name": "这类头痛千万别大意",
                "guanggao_at": "0",
                "title_topic_summary": "牙疼、高血压引起的头痛，可能比较常见。但是，如果你经历过那种仿佛“头要裂开”的剧痛，难以入眠，那就要小心了，这可能是脑瘤的信号！遇到这种情况，建议及时就医检查，早发现早治疗！",
                "create_at": "1732689308",
                "is_hotsearch": "-1",
                "icon": "",
                "create_dt": "2024-11-27 14:35:08",
                "input_time": "1732689308",
                "is_ad": 0,
                "news_id": "HB-1-qichefe_superpage_hottopic/hottopic-topic_4549064",
                "wburl": "https://s.weibo.com/weibo?q=%23%E8%BF%99%E7%B1%BB%E5%A4%B4%E7%97%9B%E5%8D%83%E4%B8%87%E5%88%AB%E5%A4%A7%E6%84%8F%23"
            },
            {
                "id": "16990",
                "title": "头疼怕冷可以低头找这个穴位按按",
                "titles": [
                    "头疼怕冷可以低头找这个穴位按按"
                ],
                "hot_icon_type": "0",
                "sort_last": "-1",
                "wap_url": "sinaweibo://searchall?q=%23%E5%A4%B4%E7%96%BC%E6%80%95%E5%86%B7%E5%8F%AF%E4%BB%A5%E4%BD%8E%E5%A4%B4%E6%89%BE%E8%BF%99%E4%B8%AA%E7%A9%B4%E4%BD%8D%E6%8C%89%E6%8C%89%23",
                "sort_now": "34",
                "hot_val": "27051",
                "show_times": "1",
                "hot_icon_url": "",
                "wb_jump_type": 1,
                "start_at": "1732694787",
                "pics": [],
                "title_pic": "",
                "title_type": "0",
                "original_topic_name": "头疼怕冷可以低头找这个穴位按按",
                "guanggao_at": "0",
                "title_topic_summary": "一到冬季就头疼、流清鼻涕，手脚冰凉还怕冷？别担心！可以尝试按这个穴位缓解：慢慢低头，找到颈部最高点第七颈椎，下方凹陷处就是大椎穴，每次按揉大椎穴3到5分钟，起到一个温阳通络的作用。快收藏用起来吧！",
                "create_at": "1732694787",
                "is_hotsearch": "-1",
                "icon": "",
                "create_dt": "2024-11-27 16:06:27",
                "input_time": "1732694787",
                "is_ad": 0,
                "news_id": "HB-1-qichefe_superpage_hottopic/hottopic-topic_4550963",
                "wburl": "https://s.weibo.com/weibo?q=%23%E5%A4%B4%E7%96%BC%E6%80%95%E5%86%B7%E5%8F%AF%E4%BB%A5%E4%BD%8E%E5%A4%B4%E6%89%BE%E8%BF%99%E4%B8%AA%E7%A9%B4%E4%BD%8D%E6%8C%89%E6%8C%89%23"
            },
            {
                "id": "16864",
                "title": "加湿器不清洁可能引发肺炎",
                "titles": [
                    "加湿器不清洁可能引发肺炎"
                ],
                "hot_icon_type": "0",
                "sort_last": "0",
                "wap_url": "sinaweibo://searchall?q=%23%E5%8A%A0%E6%B9%BF%E5%99%A8%E4%B8%8D%E6%B8%85%E6%B4%81%E5%8F%AF%E8%83%BD%E5%BC%95%E5%8F%91%E8%82%BA%E7%82%8E%23",
                "sort_now": "35",
                "hot_val": "26407",
                "show_times": "1",
                "hot_icon_url": "",
                "wb_jump_type": 1,
                "start_at": "1732587261",
                "pics": [],
                "title_pic": "",
                "title_type": "0",
                "original_topic_name": "加湿器不清洁可能引发肺炎",
                "guanggao_at": "0",
                "title_topic_summary": "冬季为了缓解空气干燥，很多人会选择在室内使用加湿器。需要注意的是，若不及时清洁，加湿器中的水容易被真菌或细菌污染，加湿器使用不当会引发多种疾病。医生提醒，加湿器要定期清洁或消毒，保持内部干净。",
                "create_at": "1732587261",
                "is_hotsearch": "-1",
                "icon": "",
                "create_dt": "2024-11-26 10:14:21",
                "input_time": "1732587261",
                "is_ad": 0,
                "news_id": "HB-1-qichefe_superpage_hottopic/hottopic-topic_4546655",
                "wburl": "https://s.weibo.com/weibo?q=%23%E5%8A%A0%E6%B9%BF%E5%99%A8%E4%B8%8D%E6%B8%85%E6%B4%81%E5%8F%AF%E8%83%BD%E5%BC%95%E5%8F%91%E8%82%BA%E7%82%8E%23"
            },
            {
                "id": "16860",
                "title": "都是流感有什么不同",
                "titles": [
                    "都是流感有什么不同"
                ],
                "hot_icon_type": "0",
                "sort_last": "-1",
                "wap_url": "sinaweibo://searchall?q=%23%E9%83%BD%E6%98%AF%E6%B5%81%E6%84%9F%E6%9C%89%E4%BB%80%E4%B9%88%E4%B8%8D%E5%90%8C%23",
                "sort_now": "36",
                "hot_val": "25896",
                "show_times": "1",
                "hot_icon_url": "",
                "wb_jump_type": 1,
                "start_at": "1732587189",
                "pics": [],
                "title_pic": "",
                "title_type": "0",
                "original_topic_name": "都是流感有什么不同",
                "guanggao_at": "0",
                "title_topic_summary": "",
                "create_at": "1732587189",
                "is_hotsearch": "1",
                "icon": "",
                "create_dt": "2024-11-26 10:13:09",
                "input_time": "1732587189",
                "is_ad": 0,
                "news_id": "HB-1-qichefe_superpage_hottopic/hottopic-topic_4546525",
                "wburl": "https://s.weibo.com/weibo?q=%23%E9%83%BD%E6%98%AF%E6%B5%81%E6%84%9F%E6%9C%89%E4%BB%80%E4%B9%88%E4%B8%8D%E5%90%8C%23"
            },
            {
                "id": "16872",
                "title": "吃撑一次会让多个器官受到伤害",
                "titles": [
                    "吃撑一次会让多个器官受到伤害"
                ],
                "hot_icon_type": "0",
                "sort_last": "-1",
                "wap_url": "sinaweibo://searchall?q=%23%E5%90%83%E6%92%91%E4%B8%80%E6%AC%A1%E4%BC%9A%E8%AE%A9%E5%A4%9A%E4%B8%AA%E5%99%A8%E5%AE%98%E5%8F%97%E5%88%B0%E4%BC%A4%E5%AE%B3%23",
                "sort_now": "37",
                "hot_val": "25093",
                "show_times": "1",
                "hot_icon_url": "",
                "wb_jump_type": 1,
                "start_at": "1732587333",
                "pics": [],
                "title_pic": "",
                "title_type": "0",
                "original_topic_name": "吃撑一次会让多个器官受到伤害",
                "guanggao_at": "0",
                "title_topic_summary": "",
                "create_at": "1732587333",
                "is_hotsearch": "-1",
                "icon": "",
                "create_dt": "2024-11-26 10:15:33",
                "input_time": "1732587333",
                "is_ad": 0,
                "news_id": "HB-1-qichefe_superpage_hottopic/hottopic-topic_4546841",
                "wburl": "https://s.weibo.com/weibo?q=%23%E5%90%83%E6%92%91%E4%B8%80%E6%AC%A1%E4%BC%9A%E8%AE%A9%E5%A4%9A%E4%B8%AA%E5%99%A8%E5%AE%98%E5%8F%97%E5%88%B0%E4%BC%A4%E5%AE%B3%23"
            },
            {
                "id": "16859",
                "title": "这3个动作助你入睡",
                "titles": [
                    "这3个动作助你入睡"
                ],
                "hot_icon_type": "0",
                "sort_last": "1",
                "wap_url": "sinaweibo://searchall?q=%23%E8%BF%993%E4%B8%AA%E5%8A%A8%E4%BD%9C%E5%8A%A9%E4%BD%A0%E5%85%A5%E7%9D%A1%23",
                "sort_now": "38",
                "hot_val": "24669",
                "show_times": "1",
                "hot_icon_url": "",
                "wb_jump_type": 1,
                "start_at": "1732587163",
                "pics": [],
                "title_pic": "",
                "title_type": "0",
                "original_topic_name": "这3个动作助你入睡",
                "guanggao_at": "0",
                "title_topic_summary": "①搓掌熨目；②轻抚头发；③缓摩腹部。愿你睡个好觉！",
                "create_at": "1732587163",
                "is_hotsearch": "-1",
                "icon": "",
                "create_dt": "2024-11-26 10:12:43",
                "input_time": "1732587163",
                "is_ad": 0,
                "news_id": "HB-1-qichefe_superpage_hottopic/hottopic-topic_4546484",
                "wburl": "https://s.weibo.com/weibo?q=%23%E8%BF%993%E4%B8%AA%E5%8A%A8%E4%BD%9C%E5%8A%A9%E4%BD%A0%E5%85%A5%E7%9D%A1%23"
            },
            {
                "id": "16811",
                "title": "每天吃坚果死亡综合风险降低23%",
                "titles": [
                    "每天吃坚果死亡综合风险降低23%"
                ],
                "hot_icon_type": "0",
                "sort_last": "1",
                "wap_url": "sinaweibo://searchall?q=%E6%AF%8F%E5%A4%A9%E5%90%83%E5%9D%9A%E6%9E%9C%E6%AD%BB%E4%BA%A1%E7%BB%BC%E5%90%88%E9%A3%8E%E9%99%A9%E9%99%8D%E4%BD%8E23%25",
                "sort_now": "39",
                "hot_val": "24604",
                "show_times": "1",
                "hot_icon_url": "",
                "wb_jump_type": 2,
                "start_at": "1732501506",
                "pics": [],
                "title_pic": "",
                "title_type": "0",
                "original_topic_name": "每天吃坚果死亡综合风险降低23%",
                "guanggao_at": "0",
                "title_topic_summary": "11月18日《Age and Ageing 》期刊发表的一项研究显示，每天吃坚果可延长健康寿命，与残疾、痴呆或死亡综合风险降低23%相关。",
                "create_at": "1732501506",
                "is_hotsearch": "-1",
                "icon": "",
                "create_dt": "2024-11-25 10:25:06",
                "input_time": "1732501506",
                "is_ad": 0,
                "news_id": "HB-1-qichefe_superpage_hottopic/hottopic-topic_4544074",
                "wburl": "https://s.weibo.com/weibo?q=%E6%AF%8F%E5%A4%A9%E5%90%83%E5%9D%9A%E6%9E%9C%E6%AD%BB%E4%BA%A1%E7%BB%BC%E5%90%88%E9%A3%8E%E9%99%A9%E9%99%8D%E4%BD%8E23%25"
            },
            {
                "id": "16969",
                "title": "气血不足的人更容易衰老",
                "titles": [
                    "气血不足的人更容易衰老"
                ],
                "hot_icon_type": "0",
                "sort_last": "-1",
                "wap_url": "sinaweibo://searchall?q=%23%E6%B0%94%E8%A1%80%E4%B8%8D%E8%B6%B3%E7%9A%84%E4%BA%BA%E6%9B%B4%E5%AE%B9%E6%98%93%E8%A1%B0%E8%80%81%23",
                "sort_now": "40",
                "hot_val": "24182",
                "show_times": "1",
                "hot_icon_url": "",
                "wb_jump_type": 1,
                "start_at": "1732689684",
                "pics": [],
                "title_pic": "",
                "title_type": "0",
                "original_topic_name": "气血不足的人更容易衰老",
                "guanggao_at": "0",
                "title_topic_summary": "",
                "create_at": "1732689684",
                "is_hotsearch": "-1",
                "icon": "",
                "create_dt": "2024-11-27 14:41:24",
                "input_time": "1732689684",
                "is_ad": 0,
                "news_id": "HB-1-qichefe_superpage_hottopic/hottopic-topic_4549805",
                "wburl": "https://s.weibo.com/weibo?q=%23%E6%B0%94%E8%A1%80%E4%B8%8D%E8%B6%B3%E7%9A%84%E4%BA%BA%E6%9B%B4%E5%AE%B9%E6%98%93%E8%A1%B0%E8%80%81%23"
            }
        ],
        "from": "n"
    }
}