{
    "code": "1000",
    "msg": "成功",
    "data": {
        "zhiding": [],
        "list": [
            {
                "id": "18406",
                "title": "感染了甲流会有什么症状",
                "titles": [
                    "感染了甲流会有什么症状"
                ],
                "hot_icon_type": "3",
                "sort_last": "1",
                "wap_url": "sinaweibo://searchall?q=%23%E6%84%9F%E6%9F%93%E4%BA%86%E7%94%B2%E6%B5%81%E4%BC%9A%E6%9C%89%E4%BB%80%E4%B9%88%E7%97%87%E7%8A%B6%23",
                "sort_now": "1",
                "hot_val": "120267",
                "show_times": "1",
                "hot_icon_url": "",
                "wb_jump_type": 1,
                "start_at": "1736130030",
                "pics": [],
                "title_pic": "",
                "title_type": "0",
                "original_topic_name": "感染了甲流会有什么症状",
                "guanggao_at": "0",
                "title_topic_summary": "全国流感病毒阳性率快速上升，当前流感病毒99%以上为甲型H1N1流感亚型。",
                "create_at": "1736130030",
                "is_hotsearch": "1",
                "icon": "//simg.s.weibo.com/20200928_hot.png",
                "create_dt": "2025-01-06 10:20:30",
                "input_time": "1736130030",
                "is_ad": 0,
                "news_id": "HB-1-qichefe_superpage_hottopic/hottopic-topic_4636779",
                "wburl": "https://s.weibo.com/weibo?q=%23%E6%84%9F%E6%9F%93%E4%BA%86%E7%94%B2%E6%B5%81%E4%BC%9A%E6%9C%89%E4%BB%80%E4%B9%88%E7%97%87%E7%8A%B6%23"
            },
            {
                "id": "18443",
                "title": "得流感不能盲目使用抗菌药",
                "titles": [
                    "得流感不能盲目使用抗菌药"
                ],
                "hot_icon_type": "3",
                "sort_last": "1",
                "wap_url": "sinaweibo://searchall?q=%E5%BE%97%E6%B5%81%E6%84%9F%E4%B8%8D%E8%83%BD%E7%9B%B2%E7%9B%AE%E4%BD%BF%E7%94%A8%E6%8A%97%E8%8F%8C%E8%8D%AF",
                "sort_now": "2",
                "hot_val": "80364",
                "show_times": "1",
                "hot_icon_url": "",
                "wb_jump_type": 2,
                "start_at": "1736244262",
                "pics": [],
                "title_pic": "",
                "title_type": "0",
                "original_topic_name": "得流感不能盲目使用抗菌药",
                "guanggao_at": "0",
                "title_topic_summary": "",
                "create_at": "1736244262",
                "is_hotsearch": "-1",
                "icon": "//simg.s.weibo.com/20200928_hot.png",
                "create_dt": "2025-01-07 18:04:22",
                "input_time": "1736244262",
                "is_ad": 0,
                "news_id": "HB-1-qichefe_superpage_hottopic/hottopic-topic_4640481",
                "wburl": "https://s.weibo.com/weibo?q=%E5%BE%97%E6%B5%81%E6%84%9F%E4%B8%8D%E8%83%BD%E7%9B%B2%E7%9B%AE%E4%BD%BF%E7%94%A8%E6%8A%97%E8%8F%8C%E8%8D%AF"
            },
            {
                "id": "18442",
                "title": "肠胃不好的人更易患心理疾病",
                "titles": [
                    "肠胃不好的人更易患心理疾病"
                ],
                "hot_icon_type": "3",
                "sort_last": "1",
                "wap_url": "sinaweibo://searchall?q=%E8%82%A0%E8%83%83%E4%B8%8D%E5%A5%BD%E7%9A%84%E4%BA%BA%E6%9B%B4%E6%98%93%E6%82%A3%E5%BF%83%E7%90%86%E7%96%BE%E7%97%85",
                "sort_now": "3",
                "hot_val": "66768",
                "show_times": "1",
                "hot_icon_url": "",
                "wb_jump_type": 2,
                "start_at": "1736244182",
                "pics": [],
                "title_pic": "",
                "title_type": "0",
                "original_topic_name": "肠胃不好的人更易患心理疾病",
                "guanggao_at": "0",
                "title_topic_summary": "既往研究表明，功能性消化不良患者的心理障碍共病率高达49.3%，且症状轻重与心理疾病严重程度相关。",
                "create_at": "1736244182",
                "is_hotsearch": "-1",
                "icon": "//simg.s.weibo.com/20200928_hot.png",
                "create_dt": "2025-01-07 18:03:02",
                "input_time": "1736244182",
                "is_ad": 0,
                "news_id": "HB-1-qichefe_superpage_hottopic/hottopic-topic_4640280",
                "wburl": "https://s.weibo.com/weibo?q=%E8%82%A0%E8%83%83%E4%B8%8D%E5%A5%BD%E7%9A%84%E4%BA%BA%E6%9B%B4%E6%98%93%E6%82%A3%E5%BF%83%E7%90%86%E7%96%BE%E7%97%85"
            },
            {
                "id": "18434",
                "title": "感冒要不要吃消炎药",
                "titles": [
                    "感冒要不要吃消炎药"
                ],
                "hot_icon_type": "4",
                "sort_last": "1",
                "wap_url": "sinaweibo://searchall?q=%E6%84%9F%E5%86%92%E8%A6%81%E4%B8%8D%E8%A6%81%E5%90%83%E6%B6%88%E7%82%8E%E8%8D%AF",
                "sort_now": "4",
                "hot_val": "65509",
                "show_times": "1",
                "hot_icon_url": "",
                "wb_jump_type": 2,
                "start_at": "1736220493",
                "pics": [],
                "title_pic": "",
                "title_type": "0",
                "original_topic_name": "感冒要不要吃消炎药",
                "guanggao_at": "0",
                "title_topic_summary": "",
                "create_at": "1736220493",
                "is_hotsearch": "1",
                "icon": "//simg.s.weibo.com/20200928_fei.png",
                "create_dt": "2025-01-07 11:28:13",
                "input_time": "1736220493",
                "is_ad": 0,
                "news_id": "HB-1-qichefe_superpage_hottopic/hottopic-topic_4639493",
                "wburl": "https://s.weibo.com/weibo?q=%E6%84%9F%E5%86%92%E8%A6%81%E4%B8%8D%E8%A6%81%E5%90%83%E6%B6%88%E7%82%8E%E8%8D%AF"
            },
            {
                "id": "18445",
                "title": "流感七日病程症状图",
                "titles": [
                    "流感七日病程症状图"
                ],
                "hot_icon_type": "1",
                "sort_last": "-1",
                "wap_url": "sinaweibo://searchall?q=%23%E6%B5%81%E6%84%9F%E4%B8%83%E6%97%A5%E7%97%85%E7%A8%8B%E7%97%87%E7%8A%B6%E5%9B%BE%23",
                "sort_now": "5",
                "hot_val": "58393",
                "show_times": "1",
                "hot_icon_url": "",
                "wb_jump_type": 1,
                "start_at": "1736302662",
                "pics": [],
                "title_pic": "",
                "title_type": "0",
                "original_topic_name": "流感七日病程症状图",
                "guanggao_at": "0",
                "title_topic_summary": "最近全国流感高发，近期流感99%以上是感染甲流！七日病程症状和用药图来了！",
                "create_at": "1736302662",
                "is_hotsearch": "-1",
                "icon": "//simg.s.weibo.com/20200928_new.png",
                "create_dt": "2025-01-08 10:17:42",
                "input_time": "1736302662",
                "is_ad": 0,
                "news_id": "HB-1-qichefe_superpage_hottopic/hottopic-topic_4640704",
                "wburl": "https://s.weibo.com/weibo?q=%23%E6%B5%81%E6%84%9F%E4%B8%83%E6%97%A5%E7%97%85%E7%A8%8B%E7%97%87%E7%8A%B6%E5%9B%BE%23"
            },
            {
                "id": "18424",
                "title": "喝酒应该先护肝还是先护脑",
                "titles": [
                    "喝酒应该先护肝还是先护脑"
                ],
                "hot_icon_type": "0",
                "sort_last": "1",
                "wap_url": "sinaweibo://searchall?q=%E5%96%9D%E9%85%92%E5%BA%94%E8%AF%A5%E5%85%88%E6%8A%A4%E8%82%9D%E8%BF%98%E6%98%AF%E5%85%88%E6%8A%A4%E8%84%91",
                "sort_now": "6",
                "hot_val": "54801",
                "show_times": "1",
                "hot_icon_url": "",
                "wb_jump_type": 2,
                "start_at": "1736160807",
                "pics": [],
                "title_pic": "",
                "title_type": "0",
                "original_topic_name": "喝酒应该先护肝还是先护脑",
                "guanggao_at": "0",
                "title_topic_summary": "开年聚会难免饮酒，你知道酒精的长期摄入会大大增加人脑海马体萎缩风险，从而引发记忆力下降，情绪不稳，严重者导致老年痴呆等脑损伤。@微博健康 联合@华素制药号召适度饮酒，保持风度，陪你健康过大年。",
                "create_at": "1736160807",
                "is_hotsearch": "-1",
                "icon": "",
                "create_dt": "2025-01-06 18:53:27",
                "input_time": "1736160807",
                "is_ad": 0,
                "news_id": "HB-1-qichefe_superpage_hottopic/hottopic-topic_4638476",
                "wburl": "https://s.weibo.com/weibo?q=%E5%96%9D%E9%85%92%E5%BA%94%E8%AF%A5%E5%85%88%E6%8A%A4%E8%82%9D%E8%BF%98%E6%98%AF%E5%85%88%E6%8A%A4%E8%84%91"
            },
            {
                "id": "18400",
                "title": "甲流通常全身症状比较明显",
                "titles": [
                    "甲流通常全身症状比较明显"
                ],
                "hot_icon_type": "0",
                "sort_last": "-1",
                "wap_url": "sinaweibo://searchall?q=%23%E7%94%B2%E6%B5%81%E9%80%9A%E5%B8%B8%E5%85%A8%E8%BA%AB%E7%97%87%E7%8A%B6%E6%AF%94%E8%BE%83%E6%98%8E%E6%98%BE%23",
                "sort_now": "7",
                "hot_val": "53290",
                "show_times": "1",
                "hot_icon_url": "",
                "wb_jump_type": 1,
                "start_at": "1736129898",
                "pics": [],
                "title_pic": "",
                "title_type": "0",
                "original_topic_name": "甲流通常全身症状比较明显",
                "guanggao_at": "0",
                "title_topic_summary": "近期，流感高发，据中国疾控中心最新数据，目前流感病毒阳性率持续上升，其中99%以上为甲流。全国多地疾控紧急提醒，要做好个人防护，注意防范呼吸道、肠道传染病。出现感冒症状，如何区分是普通感冒还是甲流呢？",
                "create_at": "1736129898",
                "is_hotsearch": "1",
                "icon": "",
                "create_dt": "2025-01-06 10:18:18",
                "input_time": "1736129898",
                "is_ad": 0,
                "news_id": "HB-1-qichefe_superpage_hottopic/hottopic-topic_4636550",
                "wburl": "https://s.weibo.com/weibo?q=%23%E7%94%B2%E6%B5%81%E9%80%9A%E5%B8%B8%E5%85%A8%E8%BA%AB%E7%97%87%E7%8A%B6%E6%AF%94%E8%BE%83%E6%98%8E%E6%98%BE%23"
            },
            {
                "id": "18397",
                "title": "所有人群都适合冬季进补吗",
                "titles": [
                    "所有人群都适合冬季进补吗"
                ],
                "hot_icon_type": "0",
                "sort_last": "1",
                "wap_url": "sinaweibo://searchall?q=%23%E6%89%80%E6%9C%89%E4%BA%BA%E7%BE%A4%E9%83%BD%E9%80%82%E5%90%88%E5%86%AC%E5%AD%A3%E8%BF%9B%E8%A1%A5%E5%90%97%23",
                "sort_now": "8",
                "hot_val": "45731",
                "show_times": "1",
                "hot_icon_url": "",
                "wb_jump_type": 1,
                "start_at": "1736129830",
                "pics": [],
                "title_pic": "",
                "title_type": "0",
                "original_topic_name": "所有人群都适合冬季进补吗",
                "guanggao_at": "0",
                "title_topic_summary": "",
                "create_at": "1736129830",
                "is_hotsearch": "-1",
                "icon": "",
                "create_dt": "2025-01-06 10:17:10",
                "input_time": "1736129830",
                "is_ad": 0,
                "news_id": "HB-1-qichefe_superpage_hottopic/hottopic-topic_4636400",
                "wburl": "https://s.weibo.com/weibo?q=%23%E6%89%80%E6%9C%89%E4%BA%BA%E7%BE%A4%E9%83%BD%E9%80%82%E5%90%88%E5%86%AC%E5%AD%A3%E8%BF%9B%E8%A1%A5%E5%90%97%23"
            },
            {
                "id": "18450",
                "title": "冬季警惕一氧化碳中毒注意这几点",
                "titles": [
                    "冬季警惕一氧化碳中毒注意这几点"
                ],
                "hot_icon_type": "1",
                "sort_last": "-1",
                "wap_url": "sinaweibo://searchall?q=%23%E5%86%AC%E5%AD%A3%E8%AD%A6%E6%83%95%E4%B8%80%E6%B0%A7%E5%8C%96%E7%A2%B3%E4%B8%AD%E6%AF%92%E6%B3%A8%E6%84%8F%E8%BF%99%E5%87%A0%E7%82%B9%23",
                "sort_now": "9",
                "hot_val": "41308",
                "show_times": "1",
                "hot_icon_url": "",
                "wb_jump_type": 1,
                "start_at": "1736302831",
                "pics": [],
                "title_pic": "",
                "title_type": "0",
                "original_topic_name": "冬季警惕一氧化碳中毒注意这几点",
                "guanggao_at": "0",
                "title_topic_summary": "每年冬季，都是一氧化碳中毒的高发季节。据统计，我国每年一氧化碳中毒案例有2000至3000例，而且绝大多数是在生活中引起的。那么，一旦发生一氧化碳中毒该如何急救？",
                "create_at": "1736302831",
                "is_hotsearch": "-1",
                "icon": "//simg.s.weibo.com/20200928_new.png",
                "create_dt": "2025-01-08 10:20:31",
                "input_time": "1736302831",
                "is_ad": 0,
                "news_id": "HB-1-qichefe_superpage_hottopic/hottopic-topic_4640999",
                "wburl": "https://s.weibo.com/weibo?q=%23%E5%86%AC%E5%AD%A3%E8%AD%A6%E6%83%95%E4%B8%80%E6%B0%A7%E5%8C%96%E7%A2%B3%E4%B8%AD%E6%AF%92%E6%B3%A8%E6%84%8F%E8%BF%99%E5%87%A0%E7%82%B9%23"
            },
            {
                "id": "18456",
                "title": "为什么生病时容易没胃口",
                "titles": [
                    "为什么生病时容易没胃口"
                ],
                "hot_icon_type": "1",
                "sort_last": "-1",
                "wap_url": "sinaweibo://searchall?q=%23%E4%B8%BA%E4%BB%80%E4%B9%88%E7%94%9F%E7%97%85%E6%97%B6%E5%AE%B9%E6%98%93%E6%B2%A1%E8%83%83%E5%8F%A3%23",
                "sort_now": "10",
                "hot_val": "35868",
                "show_times": "1",
                "hot_icon_url": "",
                "wb_jump_type": 1,
                "start_at": "1736303059",
                "pics": [],
                "title_pic": "",
                "title_type": "0",
                "original_topic_name": "为什么生病时容易没胃口",
                "guanggao_at": "0",
                "title_topic_summary": "",
                "create_at": "1736303059",
                "is_hotsearch": "-1",
                "icon": "//simg.s.weibo.com/20200928_new.png",
                "create_dt": "2025-01-08 10:24:19",
                "input_time": "1736303059",
                "is_ad": 0,
                "news_id": "HB-1-qichefe_superpage_hottopic/hottopic-topic_4641386",
                "wburl": "https://s.weibo.com/weibo?q=%23%E4%B8%BA%E4%BB%80%E4%B9%88%E7%94%9F%E7%97%85%E6%97%B6%E5%AE%B9%E6%98%93%E6%B2%A1%E8%83%83%E5%8F%A3%23"
            },
            {
                "id": "18455",
                "title": "发烧没胃口怎么吃才能恢复更快",
                "titles": [
                    "发烧没胃口怎么吃才能恢复更快"
                ],
                "hot_icon_type": "1",
                "sort_last": "-1",
                "wap_url": "sinaweibo://searchall?q=%23%E5%8F%91%E7%83%A7%E6%B2%A1%E8%83%83%E5%8F%A3%E6%80%8E%E4%B9%88%E5%90%83%E6%89%8D%E8%83%BD%E6%81%A2%E5%A4%8D%E6%9B%B4%E5%BF%AB%23",
                "sort_now": "11",
                "hot_val": "35822",
                "show_times": "1",
                "hot_icon_url": "",
                "wb_jump_type": 1,
                "start_at": "1736303050",
                "pics": [],
                "title_pic": "",
                "title_type": "0",
                "original_topic_name": "发烧没胃口怎么吃才能恢复更快",
                "guanggao_at": "0",
                "title_topic_summary": "",
                "create_at": "1736303050",
                "is_hotsearch": "-1",
                "icon": "//simg.s.weibo.com/20200928_new.png",
                "create_dt": "2025-01-08 10:24:10",
                "input_time": "1736303050",
                "is_ad": 0,
                "news_id": "HB-1-qichefe_superpage_hottopic/hottopic-topic_4641387",
                "wburl": "https://s.weibo.com/weibo?q=%23%E5%8F%91%E7%83%A7%E6%B2%A1%E8%83%83%E5%8F%A3%E6%80%8E%E4%B9%88%E5%90%83%E6%89%8D%E8%83%BD%E6%81%A2%E5%A4%8D%E6%9B%B4%E5%BF%AB%23"
            },
            {
                "id": "18453",
                "title": "甲流有没有特效药",
                "titles": [
                    "甲流有没有特效药"
                ],
                "hot_icon_type": "1",
                "sort_last": "-1",
                "wap_url": "sinaweibo://searchall?q=%23%E7%94%B2%E6%B5%81%E6%9C%89%E6%B2%A1%E6%9C%89%E7%89%B9%E6%95%88%E8%8D%AF%23",
                "sort_now": "12",
                "hot_val": "32400",
                "show_times": "1",
                "hot_icon_url": "",
                "wb_jump_type": 1,
                "start_at": "1736302905",
                "pics": [],
                "title_pic": "",
                "title_type": "0",
                "original_topic_name": "甲流有没有特效药",
                "guanggao_at": "0",
                "title_topic_summary": "近期甲流高发，那么甲流与普通感冒有何区别？有没有特效药？新华社《健康我来说》栏目邀请到了北京大学人民医院呼吸与危重症医科主任医师马艳良，为大家详细解答。",
                "create_at": "1736302905",
                "is_hotsearch": "1",
                "icon": "//simg.s.weibo.com/20200928_new.png",
                "create_dt": "2025-01-08 10:21:45",
                "input_time": "1736302905",
                "is_ad": 0,
                "news_id": "HB-1-qichefe_superpage_hottopic/hottopic-topic_4641196",
                "wburl": "https://s.weibo.com/weibo?q=%23%E7%94%B2%E6%B5%81%E6%9C%89%E6%B2%A1%E6%9C%89%E7%89%B9%E6%95%88%E8%8D%AF%23"
            },
            {
                "id": "18428",
                "title": "一组动作改善肩周炎",
                "titles": [
                    "一组动作改善肩周炎"
                ],
                "hot_icon_type": "0",
                "sort_last": "1",
                "wap_url": "sinaweibo://searchall?q=%23%E4%B8%80%E7%BB%84%E5%8A%A8%E4%BD%9C%E6%94%B9%E5%96%84%E8%82%A9%E5%91%A8%E7%82%8E%23",
                "sort_now": "13",
                "hot_val": "32198",
                "show_times": "1",
                "hot_icon_url": "",
                "wb_jump_type": 1,
                "start_at": "1736216398",
                "pics": [],
                "title_pic": "",
                "title_type": "0",
                "original_topic_name": "一组动作改善肩周炎",
                "guanggao_at": "0",
                "title_topic_summary": "",
                "create_at": "1736216398",
                "is_hotsearch": "1",
                "icon": "",
                "create_dt": "2025-01-07 10:19:58",
                "input_time": "1736216398",
                "is_ad": 0,
                "news_id": "HB-1-qichefe_superpage_hottopic/hottopic-topic_4638684",
                "wburl": "https://s.weibo.com/weibo?q=%23%E4%B8%80%E7%BB%84%E5%8A%A8%E4%BD%9C%E6%94%B9%E5%96%84%E8%82%A9%E5%91%A8%E7%82%8E%23"
            },
            {
                "id": "18405",
                "title": "体检查出这6种病不用焦虑",
                "titles": [
                    "体检查出这6种病不用焦虑"
                ],
                "hot_icon_type": "0",
                "sort_last": "1",
                "wap_url": "sinaweibo://searchall?q=%23%E4%BD%93%E6%A3%80%E6%9F%A5%E5%87%BA%E8%BF%996%E7%A7%8D%E7%97%85%E4%B8%8D%E7%94%A8%E7%84%A6%E8%99%91%23",
                "sort_now": "14",
                "hot_val": "31633",
                "show_times": "1",
                "hot_icon_url": "",
                "wb_jump_type": 1,
                "start_at": "1736129992",
                "pics": [],
                "title_pic": "",
                "title_type": "0",
                "original_topic_name": "体检查出这6种病不用焦虑",
                "guanggao_at": "0",
                "title_topic_summary": "",
                "create_at": "1736129992",
                "is_hotsearch": "-1",
                "icon": "",
                "create_dt": "2025-01-06 10:19:52",
                "input_time": "1736129992",
                "is_ad": 0,
                "news_id": "HB-1-qichefe_superpage_hottopic/hottopic-topic_4636668",
                "wburl": "https://s.weibo.com/weibo?q=%23%E4%BD%93%E6%A3%80%E6%9F%A5%E5%87%BA%E8%BF%996%E7%A7%8D%E7%97%85%E4%B8%8D%E7%94%A8%E7%84%A6%E8%99%91%23"
            },
            {
                "id": "18416",
                "title": "切记抗生素对流感是无效的",
                "titles": [
                    "切记抗生素对流感是无效的"
                ],
                "hot_icon_type": "0",
                "sort_last": "-1",
                "wap_url": "sinaweibo://searchall?q=%23%E5%88%87%E8%AE%B0%E6%8A%97%E7%94%9F%E7%B4%A0%E5%AF%B9%E6%B5%81%E6%84%9F%E6%98%AF%E6%97%A0%E6%95%88%E7%9A%84%23",
                "sort_now": "15",
                "hot_val": "29334",
                "show_times": "1",
                "hot_icon_url": "",
                "wb_jump_type": 1,
                "start_at": "1736145937",
                "pics": [],
                "title_pic": "",
                "title_type": "0",
                "original_topic_name": "切记抗生素对流感是无效的",
                "guanggao_at": "0",
                "title_topic_summary": "特别需要注意的是，抗生素对流感无效，抗流感病毒的药物对普通感冒也无效，切忌自行用药。",
                "create_at": "1736145937",
                "is_hotsearch": "-1",
                "icon": "",
                "create_dt": "2025-01-06 14:45:37",
                "input_time": "1736145937",
                "is_ad": 0,
                "news_id": "HB-1-qichefe_superpage_hottopic/hottopic-topic_4637389",
                "wburl": "https://s.weibo.com/weibo?q=%23%E5%88%87%E8%AE%B0%E6%8A%97%E7%94%9F%E7%B4%A0%E5%AF%B9%E6%B5%81%E6%84%9F%E6%98%AF%E6%97%A0%E6%95%88%E7%9A%84%23"
            },
            {
                "id": "18408",
                "title": "减肥失败是因为身体记得你胖过",
                "titles": [
                    "减肥失败是因为身体记得你胖过"
                ],
                "hot_icon_type": "0",
                "sort_last": "1",
                "wap_url": "sinaweibo://searchall?q=%23%E5%87%8F%E8%82%A5%E5%A4%B1%E8%B4%A5%E6%98%AF%E5%9B%A0%E4%B8%BA%E8%BA%AB%E4%BD%93%E8%AE%B0%E5%BE%97%E4%BD%A0%E8%83%96%E8%BF%87%23",
                "sort_now": "16",
                "hot_val": "28584",
                "show_times": "1",
                "hot_icon_url": "",
                "wb_jump_type": 1,
                "start_at": "1736130064",
                "pics": [],
                "title_pic": "",
                "title_type": "0",
                "original_topic_name": "减肥失败是因为身体记得你胖过",
                "guanggao_at": "0",
                "title_topic_summary": "肥胖的记忆“刻”在基因里",
                "create_at": "1736130064",
                "is_hotsearch": "-1",
                "icon": "",
                "create_dt": "2025-01-06 10:21:04",
                "input_time": "1736130064",
                "is_ad": 0,
                "news_id": "HB-1-qichefe_superpage_hottopic/hottopic-topic_4636809",
                "wburl": "https://s.weibo.com/weibo?q=%23%E5%87%8F%E8%82%A5%E5%A4%B1%E8%B4%A5%E6%98%AF%E5%9B%A0%E4%B8%BA%E8%BA%AB%E4%BD%93%E8%AE%B0%E5%BE%97%E4%BD%A0%E8%83%96%E8%BF%87%23"
            },
            {
                "id": "18437",
                "title": "熬夜真的伤肝吗",
                "titles": [
                    "熬夜真的伤肝吗"
                ],
                "hot_icon_type": "0",
                "sort_last": "-1",
                "wap_url": "sinaweibo://searchall?q=%23%E7%86%AC%E5%A4%9C%E7%9C%9F%E7%9A%84%E4%BC%A4%E8%82%9D%E5%90%97%23",
                "sort_now": "17",
                "hot_val": "28042",
                "show_times": "1",
                "hot_icon_url": "",
                "wb_jump_type": 1,
                "start_at": "1736244008",
                "pics": [],
                "title_pic": "",
                "title_type": "0",
                "original_topic_name": "熬夜真的伤肝吗",
                "guanggao_at": "0",
                "title_topic_summary": "肝脏作为我们的“解毒工厂”应该如何保护？来听听王学浩院士怎么说？",
                "create_at": "1736244008",
                "is_hotsearch": "-1",
                "icon": "",
                "create_dt": "2025-01-07 18:00:08",
                "input_time": "1736244008",
                "is_ad": 0,
                "news_id": "HB-1-qichefe_superpage_hottopic/hottopic-topic_4639836",
                "wburl": "https://s.weibo.com/weibo?q=%23%E7%86%AC%E5%A4%9C%E7%9C%9F%E7%9A%84%E4%BC%A4%E8%82%9D%E5%90%97%23"
            },
            {
                "id": "18429",
                "title": "头痛肌肉关节痛也是甲流症状",
                "titles": [
                    "头痛肌肉关节痛也是甲流症状"
                ],
                "hot_icon_type": "0",
                "sort_last": "1",
                "wap_url": "sinaweibo://searchall?q=%23%E5%A4%B4%E7%97%9B%E8%82%8C%E8%82%89%E5%85%B3%E8%8A%82%E7%97%9B%E4%B9%9F%E6%98%AF%E7%94%B2%E6%B5%81%E7%97%87%E7%8A%B6%23",
                "sort_now": "18",
                "hot_val": "26253",
                "show_times": "1",
                "hot_icon_url": "",
                "wb_jump_type": 1,
                "start_at": "1736216485",
                "pics": [],
                "title_pic": "",
                "title_type": "0",
                "original_topic_name": "头痛肌肉关节痛也是甲流症状",
                "guanggao_at": "0",
                "title_topic_summary": "",
                "create_at": "1736216485",
                "is_hotsearch": "-1",
                "icon": "",
                "create_dt": "2025-01-07 10:21:25",
                "input_time": "1736216485",
                "is_ad": 0,
                "news_id": "HB-1-qichefe_superpage_hottopic/hottopic-topic_4638789",
                "wburl": "https://s.weibo.com/weibo?q=%23%E5%A4%B4%E7%97%9B%E8%82%8C%E8%82%89%E5%85%B3%E8%8A%82%E7%97%9B%E4%B9%9F%E6%98%AF%E7%94%B2%E6%B5%81%E7%97%87%E7%8A%B6%23"
            },
            {
                "id": "18413",
                "title": "干噎酸奶蛋白质含量更高",
                "titles": [
                    "干噎酸奶蛋白质含量更高"
                ],
                "hot_icon_type": "0",
                "sort_last": "1",
                "wap_url": "sinaweibo://searchall?q=%23%E5%B9%B2%E5%99%8E%E9%85%B8%E5%A5%B6%E8%9B%8B%E7%99%BD%E8%B4%A8%E5%90%AB%E9%87%8F%E6%9B%B4%E9%AB%98%23",
                "sort_now": "19",
                "hot_val": "25886",
                "show_times": "1",
                "hot_icon_url": "",
                "wb_jump_type": 1,
                "start_at": "1736145826",
                "pics": [],
                "title_pic": "",
                "title_type": "0",
                "original_topic_name": "干噎酸奶蛋白质含量更高",
                "guanggao_at": "0",
                "title_topic_summary": "",
                "create_at": "1736145826",
                "is_hotsearch": "-1",
                "icon": "",
                "create_dt": "2025-01-06 14:43:46",
                "input_time": "1736145826",
                "is_ad": 0,
                "news_id": "HB-1-qichefe_superpage_hottopic/hottopic-topic_4637292",
                "wburl": "https://s.weibo.com/weibo?q=%23%E5%B9%B2%E5%99%8E%E9%85%B8%E5%A5%B6%E8%9B%8B%E7%99%BD%E8%B4%A8%E5%90%AB%E9%87%8F%E6%9B%B4%E9%AB%98%23"
            },
            {
                "id": "18414",
                "title": "感染甲流如何用药",
                "titles": [
                    "感染甲流如何用药"
                ],
                "hot_icon_type": "0",
                "sort_last": "1",
                "wap_url": "sinaweibo://searchall?q=%23%E6%84%9F%E6%9F%93%E7%94%B2%E6%B5%81%E5%A6%82%E4%BD%95%E7%94%A8%E8%8D%AF%23",
                "sort_now": "20",
                "hot_val": "23672",
                "show_times": "1",
                "hot_icon_url": "",
                "wb_jump_type": 1,
                "start_at": "1736145897",
                "pics": [],
                "title_pic": "",
                "title_type": "0",
                "original_topic_name": "感染甲流如何用药",
                "guanggao_at": "0",
                "title_topic_summary": "中国疾控中心监测结果显示，目前急性呼吸道传染病总体呈现持续上升趋势，全国流感病毒阳性率快速上升；当前南、北方流感病毒阳性率，99%以上为甲型H1N1流感亚型。流感用药，玛巴洛沙韦和奥司他韦有什么区别？",
                "create_at": "1736145897",
                "is_hotsearch": "-1",
                "icon": "",
                "create_dt": "2025-01-06 14:44:57",
                "input_time": "1736145897",
                "is_ad": 0,
                "news_id": "HB-1-qichefe_superpage_hottopic/hottopic-topic_4637370",
                "wburl": "https://s.weibo.com/weibo?q=%23%E6%84%9F%E6%9F%93%E7%94%B2%E6%B5%81%E5%A6%82%E4%BD%95%E7%94%A8%E8%8D%AF%23"
            },
            {
                "id": "18423",
                "title": "呼吸道感染进入高发期如何防治",
                "titles": [
                    "呼吸道感染进入高发期如何防治"
                ],
                "hot_icon_type": "0",
                "sort_last": "1",
                "wap_url": "sinaweibo://searchall?q=%E5%91%BC%E5%90%B8%E9%81%93%E6%84%9F%E6%9F%93%E8%BF%9B%E5%85%A5%E9%AB%98%E5%8F%91%E6%9C%9F%E5%A6%82%E4%BD%95%E9%98%B2%E6%B2%BB",
                "sort_now": "21",
                "hot_val": "23589",
                "show_times": "1",
                "hot_icon_url": "",
                "wb_jump_type": 2,
                "start_at": "1736160801",
                "pics": [],
                "title_pic": "",
                "title_type": "0",
                "original_topic_name": "呼吸道感染进入高发期如何防治",
                "guanggao_at": "0",
                "title_topic_summary": "",
                "create_at": "1736160801",
                "is_hotsearch": "-1",
                "icon": "",
                "create_dt": "2025-01-06 18:53:21",
                "input_time": "1736160801",
                "is_ad": 0,
                "news_id": "HB-1-qichefe_superpage_hottopic/hottopic-topic_4638470",
                "wburl": "https://s.weibo.com/weibo?q=%E5%91%BC%E5%90%B8%E9%81%93%E6%84%9F%E6%9F%93%E8%BF%9B%E5%85%A5%E9%AB%98%E5%8F%91%E6%9C%9F%E5%A6%82%E4%BD%95%E9%98%B2%E6%B2%BB"
            },
            {
                "id": "18402",
                "title": "缺觉4天就可能引发全身炎症",
                "titles": [
                    "缺觉4天就可能引发全身炎症"
                ],
                "hot_icon_type": "0",
                "sort_last": "1",
                "wap_url": "sinaweibo://searchall?q=%23%E7%BC%BA%E8%A7%894%E5%A4%A9%E5%B0%B1%E5%8F%AF%E8%83%BD%E5%BC%95%E5%8F%91%E5%85%A8%E8%BA%AB%E7%82%8E%E7%97%87%23",
                "sort_now": "22",
                "hot_val": "22082",
                "show_times": "1",
                "hot_icon_url": "",
                "wb_jump_type": 1,
                "start_at": "1736129921",
                "pics": [],
                "title_pic": "",
                "title_type": "0",
                "original_topic_name": "缺觉4天就可能引发全身炎症",
                "guanggao_at": "0",
                "title_topic_summary": "美国科学期刊《Cell（细胞）》刊登的研究发现，睡眠不足会增加脑内前列腺素D2产生，和经血脑屏障的外流，并在外周引发细胞因子风暴。研究团队设计了一种睡眠剥夺实验方法，令小鼠在96%的时间内保持清醒。4天之后，小鼠即表现出严重的全身炎症反应和多脏器衰竭。",
                "create_at": "1736129921",
                "is_hotsearch": "-1",
                "icon": "",
                "create_dt": "2025-01-06 10:18:41",
                "input_time": "1736129921",
                "is_ad": 0,
                "news_id": "HB-1-qichefe_superpage_hottopic/hottopic-topic_4636582",
                "wburl": "https://s.weibo.com/weibo?q=%23%E7%BC%BA%E8%A7%894%E5%A4%A9%E5%B0%B1%E5%8F%AF%E8%83%BD%E5%BC%95%E5%8F%91%E5%85%A8%E8%BA%AB%E7%82%8E%E7%97%87%23"
            },
            {
                "id": "18431",
                "title": "吃饭时间变一变或能缓解疲劳",
                "titles": [
                    "吃饭时间变一变或能缓解疲劳"
                ],
                "hot_icon_type": "0",
                "sort_last": "1",
                "wap_url": "sinaweibo://searchall?q=%23%E5%90%83%E9%A5%AD%E6%97%B6%E9%97%B4%E5%8F%98%E4%B8%80%E5%8F%98%E6%88%96%E8%83%BD%E7%BC%93%E8%A7%A3%E7%96%B2%E5%8A%B3%23",
                "sort_now": "23",
                "hot_val": "21744",
                "show_times": "1",
                "hot_icon_url": "",
                "wb_jump_type": 1,
                "start_at": "1736216523",
                "pics": [],
                "title_pic": "",
                "title_type": "0",
                "original_topic_name": "吃饭时间变一变或能缓解疲劳",
                "guanggao_at": "0",
                "title_topic_summary": "最近的一项研究发现，通过调整每天的进食时间，或许可以改善和缓解身体的疲劳状况！",
                "create_at": "1736216523",
                "is_hotsearch": "-1",
                "icon": "",
                "create_dt": "2025-01-07 10:22:03",
                "input_time": "1736216523",
                "is_ad": 0,
                "news_id": "HB-1-qichefe_superpage_hottopic/hottopic-topic_4638826",
                "wburl": "https://s.weibo.com/weibo?q=%23%E5%90%83%E9%A5%AD%E6%97%B6%E9%97%B4%E5%8F%98%E4%B8%80%E5%8F%98%E6%88%96%E8%83%BD%E7%BC%93%E8%A7%A3%E7%96%B2%E5%8A%B3%23"
            },
            {
                "id": "18411",
                "title": "吃烤橘子能缓解咳嗽吗",
                "titles": [
                    "吃烤橘子能缓解咳嗽吗"
                ],
                "hot_icon_type": "0",
                "sort_last": "-1",
                "wap_url": "sinaweibo://searchall?q=%23%E5%90%83%E7%83%A4%E6%A9%98%E5%AD%90%E8%83%BD%E7%BC%93%E8%A7%A3%E5%92%B3%E5%97%BD%E5%90%97%23",
                "sort_now": "24",
                "hot_val": "20760",
                "show_times": "1",
                "hot_icon_url": "",
                "wb_jump_type": 1,
                "start_at": "1736145256",
                "pics": [],
                "title_pic": "",
                "title_type": "0",
                "original_topic_name": "吃烤橘子能缓解咳嗽吗",
                "guanggao_at": "0",
                "title_topic_summary": "",
                "create_at": "1736145256",
                "is_hotsearch": "-1",
                "icon": "",
                "create_dt": "2025-01-06 14:34:16",
                "input_time": "1736145256",
                "is_ad": 0,
                "news_id": "HB-1-qichefe_superpage_hottopic/hottopic-topic_4637073",
                "wburl": "https://s.weibo.com/weibo?q=%23%E5%90%83%E7%83%A4%E6%A9%98%E5%AD%90%E8%83%BD%E7%BC%93%E8%A7%A3%E5%92%B3%E5%97%BD%E5%90%97%23"
            },
            {
                "id": "18396",
                "title": "儿童感染流感病毒后要尽早用药",
                "titles": [
                    "儿童感染流感病毒后要尽早用药"
                ],
                "hot_icon_type": "0",
                "sort_last": "0",
                "wap_url": "sinaweibo://searchall?q=%23%E5%84%BF%E7%AB%A5%E6%84%9F%E6%9F%93%E6%B5%81%E6%84%9F%E7%97%85%E6%AF%92%E5%90%8E%E8%A6%81%E5%B0%BD%E6%97%A9%E7%94%A8%E8%8D%AF%23",
                "sort_now": "25",
                "hot_val": "19616",
                "show_times": "1",
                "hot_icon_url": "",
                "wb_jump_type": 1,
                "start_at": "1736129808",
                "pics": [],
                "title_pic": "",
                "title_type": "0",
                "original_topic_name": "儿童感染流感病毒后要尽早用药",
                "guanggao_at": "0",
                "title_topic_summary": "近期呼吸道传染病高发，其中流感病毒阳性检出率上升明显。对此，在国家卫生健康委5日举行的新闻发布会上，专家表示，目前儿童呼吸道感染仍以病毒和肺炎支原体为主，其中病毒主要以流感病毒为主。",
                "create_at": "1736129808",
                "is_hotsearch": "-1",
                "icon": "",
                "create_dt": "2025-01-06 10:16:48",
                "input_time": "1736129808",
                "is_ad": 0,
                "news_id": "HB-1-qichefe_superpage_hottopic/hottopic-topic_4636379",
                "wburl": "https://s.weibo.com/weibo?q=%23%E5%84%BF%E7%AB%A5%E6%84%9F%E6%9F%93%E6%B5%81%E6%84%9F%E7%97%85%E6%AF%92%E5%90%8E%E8%A6%81%E5%B0%BD%E6%97%A9%E7%94%A8%E8%8D%AF%23"
            },
            {
                "id": "18439",
                "title": "槟榔早就被列为了一级致癌物",
                "titles": [
                    "槟榔早就被列为了一级致癌物"
                ],
                "hot_icon_type": "0",
                "sort_last": "1",
                "wap_url": "sinaweibo://searchall?q=%23%E6%A7%9F%E6%A6%94%E6%97%A9%E5%B0%B1%E8%A2%AB%E5%88%97%E4%B8%BA%E4%BA%86%E4%B8%80%E7%BA%A7%E8%87%B4%E7%99%8C%E7%89%A9%23",
                "sort_now": "26",
                "hot_val": "18476",
                "show_times": "1",
                "hot_icon_url": "",
                "wb_jump_type": 1,
                "start_at": "1736244072",
                "pics": [],
                "title_pic": "",
                "title_type": "0",
                "original_topic_name": "槟榔早就被列为了一级致癌物",
                "guanggao_at": "0",
                "title_topic_summary": "在医学界，有“10个口腔癌，9个嚼槟榔”的说法。",
                "create_at": "1736244072",
                "is_hotsearch": "-1",
                "icon": "",
                "create_dt": "2025-01-07 18:01:12",
                "input_time": "1736244072",
                "is_ad": 0,
                "news_id": "HB-1-qichefe_superpage_hottopic/hottopic-topic_4639933",
                "wburl": "https://s.weibo.com/weibo?q=%23%E6%A7%9F%E6%A6%94%E6%97%A9%E5%B0%B1%E8%A2%AB%E5%88%97%E4%B8%BA%E4%BA%86%E4%B8%80%E7%BA%A7%E8%87%B4%E7%99%8C%E7%89%A9%23"
            },
            {
                "id": "18409",
                "title": "5个对心脏有好处的手部动作",
                "titles": [
                    "5个对心脏有好处的手部动作"
                ],
                "hot_icon_type": "0",
                "sort_last": "-1",
                "wap_url": "sinaweibo://searchall?q=%235%E4%B8%AA%E5%AF%B9%E5%BF%83%E8%84%8F%E6%9C%89%E5%A5%BD%E5%A4%84%E7%9A%84%E6%89%8B%E9%83%A8%E5%8A%A8%E4%BD%9C%23",
                "sort_now": "27",
                "hot_val": "18443",
                "show_times": "1",
                "hot_icon_url": "",
                "wb_jump_type": 1,
                "start_at": "1736130111",
                "pics": [],
                "title_pic": "",
                "title_type": "0",
                "original_topic_name": "5个对心脏有好处的手部动作",
                "guanggao_at": "0",
                "title_topic_summary": "对心脏有好处的手部锻炼，每天花几分钟做做，健康从“心”开始！",
                "create_at": "1736130111",
                "is_hotsearch": "-1",
                "icon": "",
                "create_dt": "2025-01-06 10:21:51",
                "input_time": "1736130111",
                "is_ad": 0,
                "news_id": "HB-1-qichefe_superpage_hottopic/hottopic-topic_4636918",
                "wburl": "https://s.weibo.com/weibo?q=%235%E4%B8%AA%E5%AF%B9%E5%BF%83%E8%84%8F%E6%9C%89%E5%A5%BD%E5%A4%84%E7%9A%84%E6%89%8B%E9%83%A8%E5%8A%A8%E4%BD%9C%23"
            },
            {
                "id": "18419",
                "title": "2个小动作保护颈椎",
                "titles": [
                    "2个小动作保护颈椎"
                ],
                "hot_icon_type": "0",
                "sort_last": "-1",
                "wap_url": "sinaweibo://searchall?q=%232%E4%B8%AA%E5%B0%8F%E5%8A%A8%E4%BD%9C%E4%BF%9D%E6%8A%A4%E9%A2%88%E6%A4%8E%23",
                "sort_now": "28",
                "hot_val": "17943",
                "show_times": "1",
                "hot_icon_url": "",
                "wb_jump_type": 1,
                "start_at": "1736146056",
                "pics": [],
                "title_pic": "",
                "title_type": "0",
                "original_topic_name": "2个小动作保护颈椎",
                "guanggao_at": "0",
                "title_topic_summary": "①低头双手抱肩；②仰头双手向后交叉。每个动作做10-20下，有效缓解脖子不适症状！快试试吧↓↓",
                "create_at": "1736146056",
                "is_hotsearch": "-1",
                "icon": "",
                "create_dt": "2025-01-06 14:47:36",
                "input_time": "1736146056",
                "is_ad": 0,
                "news_id": "HB-1-qichefe_superpage_hottopic/hottopic-topic_4637629",
                "wburl": "https://s.weibo.com/weibo?q=%232%E4%B8%AA%E5%B0%8F%E5%8A%A8%E4%BD%9C%E4%BF%9D%E6%8A%A4%E9%A2%88%E6%A4%8E%23"
            },
            {
                "id": "18399",
                "title": "过胖过瘦都可能是气血失调",
                "titles": [
                    "过胖过瘦都可能是气血失调"
                ],
                "hot_icon_type": "0",
                "sort_last": "1",
                "wap_url": "sinaweibo://searchall?q=%23%E8%BF%87%E8%83%96%E8%BF%87%E7%98%A6%E9%83%BD%E5%8F%AF%E8%83%BD%E6%98%AF%E6%B0%94%E8%A1%80%E5%A4%B1%E8%B0%83%23",
                "sort_now": "29",
                "hot_val": "17202",
                "show_times": "1",
                "hot_icon_url": "",
                "wb_jump_type": 1,
                "start_at": "1736129892",
                "pics": [],
                "title_pic": "",
                "title_type": "0",
                "original_topic_name": "过胖过瘦都可能是气血失调",
                "guanggao_at": "0",
                "title_topic_summary": "有人因为胖而苦恼，有人因太瘦而需就医。无论哪种情况，在中医看来，都与气血密切相关。",
                "create_at": "1736129892",
                "is_hotsearch": "-1",
                "icon": "",
                "create_dt": "2025-01-06 10:18:12",
                "input_time": "1736129892",
                "is_ad": 0,
                "news_id": "HB-1-qichefe_superpage_hottopic/hottopic-topic_4636548",
                "wburl": "https://s.weibo.com/weibo?q=%23%E8%BF%87%E8%83%96%E8%BF%87%E7%98%A6%E9%83%BD%E5%8F%AF%E8%83%BD%E6%98%AF%E6%B0%94%E8%A1%80%E5%A4%B1%E8%B0%83%23"
            },
            {
                "id": "18412",
                "title": "如何辨别甲流和普通感冒",
                "titles": [
                    "如何辨别甲流和普通感冒"
                ],
                "hot_icon_type": "0",
                "sort_last": "-1",
                "wap_url": "sinaweibo://searchall?q=%23%E5%A6%82%E4%BD%95%E8%BE%A8%E5%88%AB%E7%94%B2%E6%B5%81%E5%92%8C%E6%99%AE%E9%80%9A%E6%84%9F%E5%86%92%23",
                "sort_now": "30",
                "hot_val": "16738",
                "show_times": "1",
                "hot_icon_url": "",
                "wb_jump_type": 1,
                "start_at": "1736145359",
                "pics": [],
                "title_pic": "",
                "title_type": "0",
                "original_topic_name": "如何辨别甲流和普通感冒",
                "guanggao_at": "0",
                "title_topic_summary": "河南省第三人民医院呼吸内科主任郭伟接受@大象新闻 采访称：“今年由于低温干燥的天气持续时间比较长，周围很多人都得流感了。流感病毒变异非常快，我们的疫苗可能今年对这个亚型可以，明年又变异出新的亚型，打过疫苗也可能再次感染。”",
                "create_at": "1736145359",
                "is_hotsearch": "1",
                "icon": "",
                "create_dt": "2025-01-06 14:35:59",
                "input_time": "1736145359",
                "is_ad": 0,
                "news_id": "HB-1-qichefe_superpage_hottopic/hottopic-topic_4637181",
                "wburl": "https://s.weibo.com/weibo?q=%23%E5%A6%82%E4%BD%95%E8%BE%A8%E5%88%AB%E7%94%B2%E6%B5%81%E5%92%8C%E6%99%AE%E9%80%9A%E6%84%9F%E5%86%92%23"
            },
            {
                "id": "18448",
                "title": "8种指甲形状提示疾病风险",
                "titles": [
                    "8种指甲形状提示疾病风险"
                ],
                "hot_icon_type": "1",
                "sort_last": "1",
                "wap_url": "sinaweibo://searchall?q=%238%E7%A7%8D%E6%8C%87%E7%94%B2%E5%BD%A2%E7%8A%B6%E6%8F%90%E7%A4%BA%E7%96%BE%E7%97%85%E9%A3%8E%E9%99%A9%23",
                "sort_now": "31",
                "hot_val": "16605",
                "show_times": "1",
                "hot_icon_url": "",
                "wb_jump_type": 1,
                "start_at": "1736302740",
                "pics": [],
                "title_pic": "",
                "title_type": "0",
                "original_topic_name": "8种指甲形状提示疾病风险",
                "guanggao_at": "0",
                "title_topic_summary": "健康的指甲红润、坚韧，平滑而有光泽，指甲上的月牙清晰，且呈弧形。",
                "create_at": "1736302740",
                "is_hotsearch": "-1",
                "icon": "//simg.s.weibo.com/20200928_new.png",
                "create_dt": "2025-01-08 10:19:00",
                "input_time": "1736302740",
                "is_ad": 0,
                "news_id": "HB-1-qichefe_superpage_hottopic/hottopic-topic_4640825",
                "wburl": "https://s.weibo.com/weibo?q=%238%E7%A7%8D%E6%8C%87%E7%94%B2%E5%BD%A2%E7%8A%B6%E6%8F%90%E7%A4%BA%E7%96%BE%E7%97%85%E9%A3%8E%E9%99%A9%23"
            },
            {
                "id": "18404",
                "title": "改善手脚冰凉试试这招",
                "titles": [
                    "改善手脚冰凉试试这招"
                ],
                "hot_icon_type": "0",
                "sort_last": "1",
                "wap_url": "sinaweibo://searchall?q=%23%E6%94%B9%E5%96%84%E6%89%8B%E8%84%9A%E5%86%B0%E5%87%89%E8%AF%95%E8%AF%95%E8%BF%99%E6%8B%9B%23",
                "sort_now": "32",
                "hot_val": "16092",
                "show_times": "1",
                "hot_icon_url": "",
                "wb_jump_type": 1,
                "start_at": "1736129971",
                "pics": [],
                "title_pic": "",
                "title_type": "0",
                "original_topic_name": "改善手脚冰凉试试这招",
                "guanggao_at": "0",
                "title_topic_summary": "动作要领：自然站立，两脚与肩等宽，吸气，左臂内旋上抬，右臂下沉；呼气，双手回归到腹部。在上举下按时，脚大拇指有意下压，感觉全身都在舒展发力，配合着呼吸慢慢练起来。",
                "create_at": "1736129971",
                "is_hotsearch": "-1",
                "icon": "",
                "create_dt": "2025-01-06 10:19:31",
                "input_time": "1736129971",
                "is_ad": 0,
                "news_id": "HB-1-qichefe_superpage_hottopic/hottopic-topic_4636638",
                "wburl": "https://s.weibo.com/weibo?q=%23%E6%94%B9%E5%96%84%E6%89%8B%E8%84%9A%E5%86%B0%E5%87%89%E8%AF%95%E8%AF%95%E8%BF%99%E6%8B%9B%23"
            },
            {
                "id": "18398",
                "title": "气血不足面色不好怎么办",
                "titles": [
                    "气血不足面色不好怎么办"
                ],
                "hot_icon_type": "0",
                "sort_last": "-1",
                "wap_url": "sinaweibo://searchall?q=%23%E6%B0%94%E8%A1%80%E4%B8%8D%E8%B6%B3%E9%9D%A2%E8%89%B2%E4%B8%8D%E5%A5%BD%E6%80%8E%E4%B9%88%E5%8A%9E%23",
                "sort_now": "33",
                "hot_val": "15774",
                "show_times": "1",
                "hot_icon_url": "",
                "wb_jump_type": 1,
                "start_at": "1736129867",
                "pics": [],
                "title_pic": "",
                "title_type": "0",
                "original_topic_name": "气血不足面色不好怎么办",
                "guanggao_at": "0",
                "title_topic_summary": "",
                "create_at": "1736129867",
                "is_hotsearch": "-1",
                "icon": "",
                "create_dt": "2025-01-06 10:17:47",
                "input_time": "1736129867",
                "is_ad": 0,
                "news_id": "HB-1-qichefe_superpage_hottopic/hottopic-topic_4636472",
                "wburl": "https://s.weibo.com/weibo?q=%23%E6%B0%94%E8%A1%80%E4%B8%8D%E8%B6%B3%E9%9D%A2%E8%89%B2%E4%B8%8D%E5%A5%BD%E6%80%8E%E4%B9%88%E5%8A%9E%23"
            },
            {
                "id": "18457",
                "title": "甲状腺结节真是气出来的吗",
                "titles": [
                    "甲状腺结节真是气出来的吗"
                ],
                "hot_icon_type": "1",
                "sort_last": "1",
                "wap_url": "sinaweibo://searchall?q=%23%E7%94%B2%E7%8A%B6%E8%85%BA%E7%BB%93%E8%8A%82%E7%9C%9F%E6%98%AF%E6%B0%94%E5%87%BA%E6%9D%A5%E7%9A%84%E5%90%97%23",
                "sort_now": "34",
                "hot_val": "15758",
                "show_times": "1",
                "hot_icon_url": "",
                "wb_jump_type": 1,
                "start_at": "1736303069",
                "pics": [],
                "title_pic": "",
                "title_type": "0",
                "original_topic_name": "甲状腺结节真是气出来的吗",
                "guanggao_at": "0",
                "title_topic_summary": "甲状腺癌已经成为中国第三大常见癌症，患病人数高达46万例！值得庆幸的是，甲状腺良性结节一般不会发展成癌，但如果体积过大或位置不好，也会影响甲状腺正常功能。",
                "create_at": "1736303069",
                "is_hotsearch": "-1",
                "icon": "//simg.s.weibo.com/20200928_new.png",
                "create_dt": "2025-01-08 10:24:29",
                "input_time": "1736303069",
                "is_ad": 0,
                "news_id": "HB-1-qichefe_superpage_hottopic/hottopic-topic_4641399",
                "wburl": "https://s.weibo.com/weibo?q=%23%E7%94%B2%E7%8A%B6%E8%85%BA%E7%BB%93%E8%8A%82%E7%9C%9F%E6%98%AF%E6%B0%94%E5%87%BA%E6%9D%A5%E7%9A%84%E5%90%97%23"
            },
            {
                "id": "18440",
                "title": "医生推荐按一个穴位缓解肩膀疼痛",
                "titles": [
                    "医生推荐按一个穴位缓解肩膀疼痛"
                ],
                "hot_icon_type": "0",
                "sort_last": "-1",
                "wap_url": "sinaweibo://searchall?q=%E5%8C%BB%E7%94%9F%E6%8E%A8%E8%8D%90%E6%8C%89%E4%B8%80%E4%B8%AA%E7%A9%B4%E4%BD%8D%E7%BC%93%E8%A7%A3%E8%82%A9%E8%86%80%E7%96%BC%E7%97%9B",
                "sort_now": "35",
                "hot_val": "15609",
                "show_times": "1",
                "hot_icon_url": "",
                "wb_jump_type": 2,
                "start_at": "1736244083",
                "pics": [],
                "title_pic": "",
                "title_type": "0",
                "original_topic_name": "医生推荐按一个穴位缓解肩膀疼痛",
                "guanggao_at": "0",
                "title_topic_summary": "专家给大家分享一个方法——按摩肩井穴，帮你缓解肩膀疼痛。肩井穴位于脖子根与肩膀头连线中点，用中指尖顶住，向对侧低头把筋绷紧，保持半分钟或一分钟。",
                "create_at": "1736244083",
                "is_hotsearch": "-1",
                "icon": "",
                "create_dt": "2025-01-07 18:01:23",
                "input_time": "1736244083",
                "is_ad": 0,
                "news_id": "HB-1-qichefe_superpage_hottopic/hottopic-topic_4639970",
                "wburl": "https://s.weibo.com/weibo?q=%E5%8C%BB%E7%94%9F%E6%8E%A8%E8%8D%90%E6%8C%89%E4%B8%80%E4%B8%AA%E7%A9%B4%E4%BD%8D%E7%BC%93%E8%A7%A3%E8%82%A9%E8%86%80%E7%96%BC%E7%97%9B"
            },
            {
                "id": "18422",
                "title": "得过甲流也可能感染乙流",
                "titles": [
                    "得过甲流也可能感染乙流"
                ],
                "hot_icon_type": "0",
                "sort_last": "1",
                "wap_url": "sinaweibo://searchall?q=%23%E5%BE%97%E8%BF%87%E7%94%B2%E6%B5%81%E4%B9%9F%E5%8F%AF%E8%83%BD%E6%84%9F%E6%9F%93%E4%B9%99%E6%B5%81%23",
                "sort_now": "36",
                "hot_val": "15463",
                "show_times": "1",
                "hot_icon_url": "",
                "wb_jump_type": 1,
                "start_at": "1736156192",
                "pics": [],
                "title_pic": "",
                "title_type": "0",
                "original_topic_name": "得过甲流也可能感染乙流",
                "guanggao_at": "0",
                "title_topic_summary": "近期，流感高发，据中国疾控中心最新数据，目前流感病毒阳性率持续上升，其中99%以上为甲流。",
                "create_at": "1736156192",
                "is_hotsearch": "-1",
                "icon": "",
                "create_dt": "2025-01-06 17:36:32",
                "input_time": "1736156192",
                "is_ad": 0,
                "news_id": "HB-1-qichefe_superpage_hottopic/hottopic-topic_4638224",
                "wburl": "https://s.weibo.com/weibo?q=%23%E5%BE%97%E8%BF%87%E7%94%B2%E6%B5%81%E4%B9%9F%E5%8F%AF%E8%83%BD%E6%84%9F%E6%9F%93%E4%B9%99%E6%B5%81%23"
            },
            {
                "id": "18432",
                "title": "患甲流后需警惕4种并发症",
                "titles": [
                    "患甲流后需警惕4种并发症"
                ],
                "hot_icon_type": "0",
                "sort_last": "1",
                "wap_url": "sinaweibo://searchall?q=%23%E6%82%A3%E7%94%B2%E6%B5%81%E5%90%8E%E9%9C%80%E8%AD%A6%E6%83%954%E7%A7%8D%E5%B9%B6%E5%8F%91%E7%97%87%23",
                "sort_now": "37",
                "hot_val": "15132",
                "show_times": "1",
                "hot_icon_url": "",
                "wb_jump_type": 1,
                "start_at": "1736216587",
                "pics": [],
                "title_pic": "",
                "title_type": "0",
                "original_topic_name": "患甲流后需警惕4种并发症",
                "guanggao_at": "0",
                "title_topic_summary": "",
                "create_at": "1736216587",
                "is_hotsearch": "-1",
                "icon": "",
                "create_dt": "2025-01-07 10:23:07",
                "input_time": "1736216587",
                "is_ad": 0,
                "news_id": "HB-1-qichefe_superpage_hottopic/hottopic-topic_4638934",
                "wburl": "https://s.weibo.com/weibo?q=%23%E6%82%A3%E7%94%B2%E6%B5%81%E5%90%8E%E9%9C%80%E8%AD%A6%E6%83%954%E7%A7%8D%E5%B9%B6%E5%8F%91%E7%97%87%23"
            },
            {
                "id": "18447",
                "title": "脱发跟缺乏这4种营养素有关",
                "titles": [
                    "脱发跟缺乏这4种营养素有关"
                ],
                "hot_icon_type": "1",
                "sort_last": "0",
                "wap_url": "sinaweibo://searchall?q=%23%E8%84%B1%E5%8F%91%E8%B7%9F%E7%BC%BA%E4%B9%8F%E8%BF%994%E7%A7%8D%E8%90%A5%E5%85%BB%E7%B4%A0%E6%9C%89%E5%85%B3%23",
                "sort_now": "38",
                "hot_val": "14802",
                "show_times": "1",
                "hot_icon_url": "",
                "wb_jump_type": 1,
                "start_at": "1736302734",
                "pics": [],
                "title_pic": "",
                "title_type": "0",
                "original_topic_name": "脱发跟缺乏这4种营养素有关",
                "guanggao_at": "0",
                "title_topic_summary": "除了遗传、压力等因素，饮食营养状况也会影响掉发情况。",
                "create_at": "1736302734",
                "is_hotsearch": "-1",
                "icon": "//simg.s.weibo.com/20200928_new.png",
                "create_dt": "2025-01-08 10:18:54",
                "input_time": "1736302734",
                "is_ad": 0,
                "news_id": "HB-1-qichefe_superpage_hottopic/hottopic-topic_4640823",
                "wburl": "https://s.weibo.com/weibo?q=%23%E8%84%B1%E5%8F%91%E8%B7%9F%E7%BC%BA%E4%B9%8F%E8%BF%994%E7%A7%8D%E8%90%A5%E5%85%BB%E7%B4%A0%E6%9C%89%E5%85%B3%23"
            },
            {
                "id": "18417",
                "title": "甲流不早治疗可能熬成肺炎",
                "titles": [
                    "甲流不早治疗可能熬成肺炎"
                ],
                "hot_icon_type": "0",
                "sort_last": "1",
                "wap_url": "sinaweibo://searchall?q=%23%E7%94%B2%E6%B5%81%E4%B8%8D%E6%97%A9%E6%B2%BB%E7%96%97%E5%8F%AF%E8%83%BD%E7%86%AC%E6%88%90%E8%82%BA%E7%82%8E%23",
                "sort_now": "39",
                "hot_val": "14292",
                "show_times": "1",
                "hot_icon_url": "",
                "wb_jump_type": 1,
                "start_at": "1736145973",
                "pics": [],
                "title_pic": "",
                "title_type": "0",
                "original_topic_name": "甲流不早治疗可能熬成肺炎",
                "guanggao_at": "0",
                "title_topic_summary": "",
                "create_at": "1736145973",
                "is_hotsearch": "-1",
                "icon": "",
                "create_dt": "2025-01-06 14:46:13",
                "input_time": "1736145973",
                "is_ad": 0,
                "news_id": "HB-1-qichefe_superpage_hottopic/hottopic-topic_4637450",
                "wburl": "https://s.weibo.com/weibo?q=%23%E7%94%B2%E6%B5%81%E4%B8%8D%E6%97%A9%E6%B2%BB%E7%96%97%E5%8F%AF%E8%83%BD%E7%86%AC%E6%88%90%E8%82%BA%E7%82%8E%23"
            },
            {
                "id": "18459",
                "title": "隐形传染者也是甲流主要传染源",
                "titles": [
                    "隐形传染者也是甲流主要传染源"
                ],
                "hot_icon_type": "1",
                "sort_last": "1",
                "wap_url": "sinaweibo://searchall?q=%23%E9%9A%90%E5%BD%A2%E4%BC%A0%E6%9F%93%E8%80%85%E4%B9%9F%E6%98%AF%E7%94%B2%E6%B5%81%E4%B8%BB%E8%A6%81%E4%BC%A0%E6%9F%93%E6%BA%90%23",
                "sort_now": "40",
                "hot_val": "13943",
                "show_times": "1",
                "hot_icon_url": "",
                "wb_jump_type": 1,
                "start_at": "1736303141",
                "pics": [],
                "title_pic": "",
                "title_type": "0",
                "original_topic_name": "隐形传染者也是甲流主要传染源",
                "guanggao_at": "0",
                "title_topic_summary": "",
                "create_at": "1736303141",
                "is_hotsearch": "-1",
                "icon": "//simg.s.weibo.com/20200928_new.png",
                "create_dt": "2025-01-08 10:25:41",
                "input_time": "1736303141",
                "is_ad": 0,
                "news_id": "HB-1-qichefe_superpage_hottopic/hottopic-topic_4641535",
                "wburl": "https://s.weibo.com/weibo?q=%23%E9%9A%90%E5%BD%A2%E4%BC%A0%E6%9F%93%E8%80%85%E4%B9%9F%E6%98%AF%E7%94%B2%E6%B5%81%E4%B8%BB%E8%A6%81%E4%BC%A0%E6%9F%93%E6%BA%90%23"
            }
        ],
        "from": "n"
    }
}